[
    {
        "Rk": "1",
        "Player": "Don Anielak",
        "Pos": "F",
        "Age": "24",
        "Tm": "NYK",
        "G": "1",
        "GS": "",
        "MP": "10",
        "FG": "0",
        "FGA": "4",
        "FG%": ".000",
        "3P": "",
        "3PA": "",
        "3P%": "",
        "2P": "0",
        "2PA": "4",
        "2P%": ".000",
        "eFG%": ".000",
        "FT": "3",
        "FTA": "4",
        "FT%": ".750",
        "ORB": "",
        "DRB": "",
        "TRB": "2",
        "AST": "0",
        "STL": "",
        "BLK": "",
        "TOV": "",
        "PF": "0",
        "PTS": "3"
    },
    {
        "Rk": "2",
        "Player": "Paul Arizin*",
        "Pos": "SF",
        "Age": "26",
        "Tm": "PHW",
        "G": "72",
        "GS": "",
        "MP": "2953",
        "FG": "529",
        "FGA": "1325",
        "FG%": ".399",
        "3P": "",
        "3PA": "",
        "3P%": "",
        "2P": "529",
        "2PA": "1325",
        "2P%": ".399",
        "eFG%": ".399",
        "FT": "454",
        "FTA": "585",
        "FT%": ".776",
        "ORB": "",
        "DRB": "",
        "TRB": "675",
        "AST": "210",
        "STL": "",
        "BLK": "",
        "TOV": "",
        "PF": "270",
        "PTS": "1512"
    },
    {
        "Rk": "3",
        "Player": "Jim Baechtold",
        "Pos": "SF",
        "Age": "27",
        "Tm": "NYK",
        "G": "72",
        "GS": "",
        "MP": "2536",
        "FG": "362",
        "FGA": "898",
        "FG%": ".403",
        "3P": "",
        "3PA": "",
        "3P%": "",
        "2P": "362",
        "2PA": "898",
        "2P%": ".403",
        "eFG%": ".403",
        "FT": "279",
        "FTA": "339",
        "FT%": ".823",
        "ORB": "",
        "DRB": "",
        "TRB": "307",
        "AST": "218",
        "STL": "",
        "BLK": "",
        "TOV": "",
        "PF": "202",
        "PTS": "1003"
    },
    {
        "Rk": "4",
        "Player": "Don Barksdale*",
        "Pos": "SF",
        "Age": "31",
        "Tm": "BOS",
        "G": "72",
        "GS": "",
        "MP": "1790",
        "FG": "267",
        "FGA": "699",
        "FG%": ".382",
        "3P": "",
        "3PA": "",
        "3P%": "",
        "2P": "267",
        "2PA": "699",
        "2P%": ".382",
        "eFG%": ".382",
        "FT": "220",
        "FTA": "338",
        "FT%": ".651",
        "ORB": "",
        "DRB": "",
        "TRB": "545",
        "AST": "129",
        "STL": "",
        "BLK": "",
        "TOV": "",
        "PF": "225",
        "PTS": "754"
    },
    {
        "Rk": "5",
        "Player": "Bob Brannum",
        "Pos": "PF",
        "Age": "29",
        "Tm": "BOS",
        "G": "71",
        "GS": "",
        "MP": "1623",
        "FG": "176",
        "FGA": "465",
        "FG%": ".378",
        "3P": "",
        "3PA": "",
        "3P%": "",
        "2P": "176",
        "2PA": "465",
        "2P%": ".378",
        "eFG%": ".378",
        "FT": "90",
        "FTA": "127",
        "FT%": ".709",
        "ORB": "",
        "DRB": "",
        "TRB": "492",
        "AST": "127",
        "STL": "",
        "BLK": "",
        "TOV": "",
        "PF": "232",
        "PTS": "442"
    },
    {
        "Rk": "6",
        "Player": "Carl Braun",
        "Pos": "SG",
        "Age": "27",
        "Tm": "NYK",
        "G": "71",
        "GS": "",
        "MP": "2479",
        "FG": "400",
        "FGA": "1032",
        "FG%": ".388",
        "3P": "",
        "3PA": "",
        "3P%": "",
        "2P": "400",
        "2PA": "1032",
        "2P%": ".388",
        "eFG%": ".388",
        "FT": "274",
        "FTA": "342",
        "FT%": ".801",
        "ORB": "",
        "DRB": "",
        "TRB": "295",
        "AST": "274",
        "STL": "",
        "BLK": "",
        "TOV": "",
        "PF": "208",
        "PTS": "1074"
    },
    {
        "Rk": "7",
        "Player": "Tom Brennan",
        "Pos": "SF",
        "Age": "24",
        "Tm": "PHW",
        "G": "11",
        "GS": "",
        "MP": "52",
        "FG": "5",
        "FGA": "11",
        "FG%": ".455",
        "3P": "",
        "3PA": "",
        "3P%": "",
        "2P": "5",
        "2PA": "11",
        "2P%": ".455",
        "eFG%": ".455",
        "FT": "0",
        "FTA": "0",
        "FT%": "",
        "ORB": "",
        "DRB": "",
        "TRB": "5",
        "AST": "2",
        "STL": "",
        "BLK": "",
        "TOV": "",
        "PF": "5",
        "PTS": "10"
    },
    {
        "Rk": "8",
        "Player": "Frankie Brian",
        "Pos": "SG",
        "Age": "31",
        "Tm": "FTW",
        "G": "71",
        "GS": "",
        "MP": "1381",
        "FG": "237",
        "FGA": "623",
        "FG%": ".380",
        "3P": "",
        "3PA": "",
        "3P%": "",
        "2P": "237",
        "2PA": "623",
        "2P%": ".380",
        "eFG%": ".380",
        "FT": "217",
        "FTA": "255",
        "FT%": ".851",
        "ORB": "",
        "DRB": "",
        "TRB": "127",
        "AST": "142",
        "STL": "",
        "BLK": "",
        "TOV": "",
        "PF": "133",
        "PTS": "691"
    },
    {
        "Rk": "9",
        "Player": "Bill Calhoun",
        "Pos": "SG",
        "Age": "27",
        "Tm": "MLH",
        "G": "69",
        "GS": "",
        "MP": "2109",
        "FG": "144",
        "FGA": "480",
        "FG%": ".300",
        "3P": "",
        "3PA": "",
        "3P%": "",
        "2P": "144",
        "2PA": "480",
        "2P%": ".300",
        "eFG%": ".300",
        "FT": "166",
        "FTA": "236",
        "FT%": ".703",
        "ORB": "",
        "DRB": "",
        "TRB": "290",
        "AST": "235",
        "STL": "",
        "BLK": "",
        "TOV": "",
        "PF": "181",
        "PTS": "454"
    },
    {
        "Rk": "10",
        "Player": "Bob Carney",
        "Pos": "SG",
        "Age": "22",
        "Tm": "MNL",
        "G": "19",
        "GS": "",
        "MP": "244",
        "FG": "24",
        "FGA": "64",
        "FG%": ".375",
        "3P": "",
        "3PA": "",
        "3P%": "",
        "2P": "24",
        "2PA": "64",
        "2P%": ".375",
        "eFG%": ".375",
        "FT": "21",
        "FTA": "40",
        "FT%": ".525",
        "ORB": "",
        "DRB": "",
        "TRB": "45",
        "AST": "16",
        "STL": "",
        "BLK": "",
        "TOV": "",
        "PF": "36",
        "PTS": "69"
    },
    {
        "Rk": "11",
        "Player": "Fred Christ",
        "Pos": "G",
        "Age": "24",
        "Tm": "NYK",
        "G": "6",
        "GS": "",
        "MP": "48",
        "FG": "5",
        "FGA": "18",
        "FG%": ".278",
        "3P": "",
        "3PA": "",
        "3P%": "",
        "2P": "5",
        "2PA": "18",
        "2P%": ".278",
        "eFG%": ".278",
        "FT": "10",
        "FTA": "11",
        "FT%": ".909",
        "ORB": "",
        "DRB": "",
        "TRB": "8",
        "AST": "7",
        "STL": "",
        "BLK": "",
        "TOV": "",
        "PF": "3",
        "PTS": "20"
    },
    {
        "Rk": "12",
        "Player": "Cal Christensen",
        "Pos": "SF",
        "Age": "27",
        "Tm": "ROC",
        "G": "71",
        "GS": "",
        "MP": "1204",
        "FG": "114",
        "FGA": "305",
        "FG%": ".374",
        "3P": "",
        "3PA": "",
        "3P%": "",
        "2P": "114",
        "2PA": "305",
        "2P%": ".374",
        "eFG%": ".374",
        "FT": "124",
        "FTA": "206",
        "FT%": ".602",
        "ORB": "",
        "DRB": "",
        "TRB": "388",
        "AST": "104",
        "STL": "",
        "BLK": "",
        "TOV": "",
        "PF": "174",
        "PTS": "352"
    },
    {
        "Rk": "13",
        "Player": "Nathaniel Clifton*",
        "Pos": "PF",
        "Age": "32",
        "Tm": "NYK",
        "G": "72",
        "GS": "",
        "MP": "2390",
        "FG": "360",
        "FGA": "932",
        "FG%": ".386",
        "3P": "",
        "3PA": "",
        "3P%": "",
        "2P": "360",
        "2PA": "932",
        "2P%": ".386",
        "eFG%": ".386",
        "FT": "224",
        "FTA": "328",
        "FT%": ".683",
        "ORB": "",
        "DRB": "",
        "TRB": "612",
        "AST": "198",
        "STL": "",
        "BLK": "",
        "TOV": "",
        "PF": "221",
        "PTS": "944"
    },
    {
        "Rk": "14",
        "Player": "Jack Coleman",
        "Pos": "PF",
        "Age": "30",
        "Tm": "ROC",
        "G": "72",
        "GS": "",
        "MP": "2482",
        "FG": "400",
        "FGA": "866",
        "FG%": ".462",
        "3P": "",
        "3PA": "",
        "3P%": "",
        "2P": "400",
        "2PA": "866",
        "2P%": ".462",
        "eFG%": ".462",
        "FT": "124",
        "FTA": "183",
        "FT%": ".678",
        "ORB": "",
        "DRB": "",
        "TRB": "729",
        "AST": "232",
        "STL": "",
        "BLK": "",
        "TOV": "",
        "PF": "201",
        "PTS": "924"
    },
    {
        "Rk": "15",
        "Player": "Bert Cook",
        "Pos": "SG",
        "Age": "25",
        "Tm": "NYK",
        "G": "37",
        "GS": "",
        "MP": "424",
        "FG": "42",
        "FGA": "133",
        "FG%": ".316",
        "3P": "",
        "3PA": "",
        "3P%": "",
        "2P": "42",
        "2PA": "133",
        "2P%": ".316",
        "eFG%": ".316",
        "FT": "34",
        "FTA": "50",
        "FT%": ".680",
        "ORB": "",
        "DRB": "",
        "TRB": "72",
        "AST": "33",
        "STL": "",
        "BLK": "",
        "TOV": "",
        "PF": "39",
        "PTS": "118"
    },
    {
        "Rk": "16",
        "Player": "Chuck Cooper*",
        "Pos": "PF",
        "Age": "28",
        "Tm": "MLH",
        "G": "70",
        "GS": "",
        "MP": "1749",
        "FG": "193",
        "FGA": "569",
        "FG%": ".339",
        "3P": "",
        "3PA": "",
        "3P%": "",
        "2P": "193",
        "2PA": "569",
        "2P%": ".339",
        "eFG%": ".339",
        "FT": "187",
        "FTA": "249",
        "FT%": ".751",
        "ORB": "",
        "DRB": "",
        "TRB": "385",
        "AST": "151",
        "STL": "",
        "BLK": "",
        "TOV": "",
        "PF": "210",
        "PTS": "573"
    },
    {
        "Rk": "17",
        "Player": "Larry Costello",
        "Pos": "PG",
        "Age": "23",
        "Tm": "PHW",
        "G": "19",
        "GS": "",
        "MP": "463",
        "FG": "46",
        "FGA": "139",
        "FG%": ".331",
        "3P": "",
        "3PA": "",
        "3P%": "",
        "2P": "46",
        "2PA": "139",
        "2P%": ".331",
        "eFG%": ".331",
        "FT": "26",
        "FTA": "32",
        "FT%": ".813",
        "ORB": "",
        "DRB": "",
        "TRB": "49",
        "AST": "78",
        "STL": "",
        "BLK": "",
        "TOV": "",
        "PF": "37",
        "PTS": "118"
    },
    {
        "Rk": "18",
        "Player": "Bob Cousy*",
        "Pos": "PG",
        "Age": "26",
        "Tm": "BOS",
        "G": "71",
        "GS": "",
        "MP": "2747",
        "FG": "522",
        "FGA": "1316",
        "FG%": ".397",
        "3P": "",
        "3PA": "",
        "3P%": "",
        "2P": "522",
        "2PA": "1316",
        "2P%": ".397",
        "eFG%": ".397",
        "FT": "460",
        "FTA": "570",
        "FT%": ".807",
        "ORB": "",
        "DRB": "",
        "TRB": "424",
        "AST": "557",
        "STL": "",
        "BLK": "",
        "TOV": "",
        "PF": "165",
        "PTS": "1504"
    },
    {
        "Rk": "19",
        "Player": "Bob Davies*",
        "Pos": "PG",
        "Age": "35",
        "Tm": "ROC",
        "G": "72",
        "GS": "",
        "MP": "1870",
        "FG": "326",
        "FGA": "785",
        "FG%": ".415",
        "3P": "",
        "3PA": "",
        "3P%": "",
        "2P": "326",
        "2PA": "785",
        "2P%": ".415",
        "eFG%": ".415",
        "FT": "220",
        "FTA": "293",
        "FT%": ".751",
        "ORB": "",
        "DRB": "",
        "TRB": "205",
        "AST": "355",
        "STL": "",
        "BLK": "",
        "TOV": "",
        "PF": "220",
        "PTS": "872"
    },
    {
        "Rk": "20",
        "Player": "Walt Davis",
        "Pos": "C",
        "Age": "24",
        "Tm": "PHW",
        "G": "61",
        "GS": "",
        "MP": "766",
        "FG": "70",
        "FGA": "182",
        "FG%": ".385",
        "3P": "",
        "3PA": "",
        "3P%": "",
        "2P": "70",
        "2PA": "182",
        "2P%": ".385",
        "eFG%": ".385",
        "FT": "35",
        "FTA": "48",
        "FT%": ".729",
        "ORB": "",
        "DRB": "",
        "TRB": "206",
        "AST": "36",
        "STL": "",
        "BLK": "",
        "TOV": "",
        "PF": "100",
        "PTS": "175"
    },
    {
        "Rk": "Rk",
        "Player": "Player",
        "Pos": "Pos",
        "Age": "Age",
        "Tm": "Tm",
        "G": "G",
        "GS": "GS",
        "MP": "MP",
        "FG": "FG",
        "FGA": "FGA",
        "FG%": "FG%",
        "3P": "3P",
        "3PA": "3PA",
        "3P%": "3P%",
        "2P": "2P",
        "2PA": "2PA",
        "2P%": "2P%",
        "eFG%": "eFG%",
        "FT": "FT",
        "FTA": "FTA",
        "FT%": "FT%",
        "ORB": "ORB",
        "DRB": "DRB",
        "TRB": "TRB",
        "AST": "AST",
        "STL": "STL",
        "BLK": "BLK",
        "TOV": "TOV",
        "PF": "PF",
        "PTS": "PTS"
    },
    {
        "Rk": "21",
        "Player": "George Dempsey",
        "Pos": "SG",
        "Age": "25",
        "Tm": "PHW",
        "G": "48",
        "GS": "",
        "MP": "1387",
        "FG": "127",
        "FGA": "360",
        "FG%": ".353",
        "3P": "",
        "3PA": "",
        "3P%": "",
        "2P": "127",
        "2PA": "360",
        "2P%": ".353",
        "eFG%": ".353",
        "FT": "98",
        "FTA": "141",
        "FT%": ".695",
        "ORB": "",
        "DRB": "",
        "TRB": "236",
        "AST": "174",
        "STL": "",
        "BLK": "",
        "TOV": "",
        "PF": "141",
        "PTS": "352"
    },
    {
        "Rk": "22",
        "Player": "Fred Diute",
        "Pos": "SG",
        "Age": "26",
        "Tm": "MLH",
        "G": "7",
        "GS": "",
        "MP": "72",
        "FG": "2",
        "FGA": "21",
        "FG%": ".095",
        "3P": "",
        "3PA": "",
        "3P%": "",
        "2P": "2",
        "2PA": "21",
        "2P%": ".095",
        "eFG%": ".095",
        "FT": "7",
        "FTA": "12",
        "FT%": ".583",
        "ORB": "",
        "DRB": "",
        "TRB": "13",
        "AST": "4",
        "STL": "",
        "BLK": "",
        "TOV": "",
        "PF": "12",
        "PTS": "11"
    },
    {
        "Rk": "23",
        "Player": "Dick Farley",
        "Pos": "SG",
        "Age": "22",
        "Tm": "SYR",
        "G": "69",
        "GS": "",
        "MP": "1113",
        "FG": "136",
        "FGA": "353",
        "FG%": ".385",
        "3P": "",
        "3PA": "",
        "3P%": "",
        "2P": "136",
        "2PA": "353",
        "2P%": ".385",
        "eFG%": ".385",
        "FT": "136",
        "FTA": "201",
        "FT%": ".677",
        "ORB": "",
        "DRB": "",
        "TRB": "167",
        "AST": "111",
        "STL": "",
        "BLK": "",
        "TOV": "",
        "PF": "145",
        "PTS": "408"
    },
    {
        "Rk": "24",
        "Player": "Ray Felix",
        "Pos": "C",
        "Age": "24",
        "Tm": "NYK",
        "G": "72",
        "GS": "",
        "MP": "2024",
        "FG": "364",
        "FGA": "832",
        "FG%": ".438",
        "3P": "",
        "3PA": "",
        "3P%": "",
        "2P": "364",
        "2PA": "832",
        "2P%": ".438",
        "eFG%": ".438",
        "FT": "310",
        "FTA": "498",
        "FT%": ".622",
        "ORB": "",
        "DRB": "",
        "TRB": "818",
        "AST": "67",
        "STL": "",
        "BLK": "",
        "TOV": "",
        "PF": "286",
        "PTS": "1038"
    },
    {
        "Rk": "25",
        "Player": "Danny Finn",
        "Pos": "PG",
        "Age": "26",
        "Tm": "PHW",
        "G": "43",
        "GS": "",
        "MP": "820",
        "FG": "77",
        "FGA": "265",
        "FG%": ".291",
        "3P": "",
        "3PA": "",
        "3P%": "",
        "2P": "77",
        "2PA": "265",
        "2P%": ".291",
        "eFG%": ".291",
        "FT": "53",
        "FTA": "86",
        "FT%": ".616",
        "ORB": "",
        "DRB": "",
        "TRB": "157",
        "AST": "155",
        "STL": "",
        "BLK": "",
        "TOV": "",
        "PF": "114",
        "PTS": "207"
    },
    {
        "Rk": "26",
        "Player": "Larry Foust",
        "Pos": "C",
        "Age": "26",
        "Tm": "FTW",
        "G": "70",
        "GS": "",
        "MP": "2264",
        "FG": "398",
        "FGA": "818",
        "FG%": ".487",
        "3P": "",
        "3PA": "",
        "3P%": "",
        "2P": "398",
        "2PA": "818",
        "2P%": ".487",
        "eFG%": ".487",
        "FT": "393",
        "FTA": "513",
        "FT%": ".766",
        "ORB": "",
        "DRB": "",
        "TRB": "700",
        "AST": "118",
        "STL": "",
        "BLK": "",
        "TOV": "",
        "PF": "264",
        "PTS": "1189"
    },
    {
        "Rk": "27",
        "Player": "Jim Fritsche",
        "Pos": "PF",
        "Age": "23",
        "Tm": "FTW",
        "G": "16",
        "GS": "",
        "MP": "151",
        "FG": "16",
        "FGA": "48",
        "FG%": ".333",
        "3P": "",
        "3PA": "",
        "3P%": "",
        "2P": "16",
        "2PA": "48",
        "2P%": ".333",
        "eFG%": ".333",
        "FT": "13",
        "FTA": "16",
        "FT%": ".813",
        "ORB": "",
        "DRB": "",
        "TRB": "32",
        "AST": "4",
        "STL": "",
        "BLK": "",
        "TOV": "",
        "PF": "28",
        "PTS": "45"
    },
    {
        "Rk": "28",
        "Player": "Bill Gabor",
        "Pos": "SG",
        "Age": "32",
        "Tm": "SYR",
        "G": "3",
        "GS": "",
        "MP": "47",
        "FG": "7",
        "FGA": "22",
        "FG%": ".318",
        "3P": "",
        "3PA": "",
        "3P%": "",
        "2P": "7",
        "2PA": "22",
        "2P%": ".318",
        "eFG%": ".318",
        "FT": "3",
        "FTA": "5",
        "FT%": ".600",
        "ORB": "",
        "DRB": "",
        "TRB": "5",
        "AST": "11",
        "STL": "",
        "BLK": "",
        "TOV": "",
        "PF": "6",
        "PTS": "17"
    },
    {
        "Rk": "29",
        "Player": "Harry Gallatin*",
        "Pos": "PF",
        "Age": "27",
        "Tm": "NYK",
        "G": "72",
        "GS": "",
        "MP": "2548",
        "FG": "330",
        "FGA": "859",
        "FG%": ".384",
        "3P": "",
        "3PA": "",
        "3P%": "",
        "2P": "330",
        "2PA": "859",
        "2P%": ".384",
        "eFG%": ".384",
        "FT": "393",
        "FTA": "483",
        "FT%": ".814",
        "ORB": "",
        "DRB": "",
        "TRB": "995",
        "AST": "176",
        "STL": "",
        "BLK": "",
        "TOV": "",
        "PF": "206",
        "PTS": "1053"
    },
    {
        "Rk": "30",
        "Player": "Jack George",
        "Pos": "PG",
        "Age": "26",
        "Tm": "PHW",
        "G": "68",
        "GS": "",
        "MP": "2480",
        "FG": "291",
        "FGA": "756",
        "FG%": ".385",
        "3P": "",
        "3PA": "",
        "3P%": "",
        "2P": "291",
        "2PA": "756",
        "2P%": ".385",
        "eFG%": ".385",
        "FT": "192",
        "FTA": "291",
        "FT%": ".660",
        "ORB": "",
        "DRB": "",
        "TRB": "302",
        "AST": "359",
        "STL": "",
        "BLK": "",
        "TOV": "",
        "PF": "191",
        "PTS": "774"
    },
    {
        "Rk": "31",
        "Player": "Joe Graboski",
        "Pos": "PF",
        "Age": "25",
        "Tm": "PHW",
        "G": "70",
        "GS": "",
        "MP": "2515",
        "FG": "373",
        "FGA": "1096",
        "FG%": ".340",
        "3P": "",
        "3PA": "",
        "3P%": "",
        "2P": "373",
        "2PA": "1096",
        "2P%": ".340",
        "eFG%": ".340",
        "FT": "208",
        "FTA": "303",
        "FT%": ".686",
        "ORB": "",
        "DRB": "",
        "TRB": "636",
        "AST": "182",
        "STL": "",
        "BLK": "",
        "TOV": "",
        "PF": "259",
        "PTS": "954"
    },
    {
        "Rk": "32",
        "Player": "Chuck Grigsby",
        "Pos": "G",
        "Age": "26",
        "Tm": "NYK",
        "G": "7",
        "GS": "",
        "MP": "45",
        "FG": "7",
        "FGA": "19",
        "FG%": ".368",
        "3P": "",
        "3PA": "",
        "3P%": "",
        "2P": "7",
        "2PA": "19",
        "2P%": ".368",
        "eFG%": ".368",
        "FT": "2",
        "FTA": "8",
        "FT%": ".250",
        "ORB": "",
        "DRB": "",
        "TRB": "11",
        "AST": "7",
        "STL": "",
        "BLK": "",
        "TOV": "",
        "PF": "9",
        "PTS": "16"
    },
    {
        "Rk": "33",
        "Player": "Alex Hannum*",
        "Pos": "PF",
        "Age": "31",
        "Tm": "MLH",
        "G": "53",
        "GS": "",
        "MP": "1088",
        "FG": "126",
        "FGA": "358",
        "FG%": ".352",
        "3P": "",
        "3PA": "",
        "3P%": "",
        "2P": "126",
        "2PA": "358",
        "2P%": ".352",
        "eFG%": ".352",
        "FT": "61",
        "FTA": "107",
        "FT%": ".570",
        "ORB": "",
        "DRB": "",
        "TRB": "245",
        "AST": "105",
        "STL": "",
        "BLK": "",
        "TOV": "",
        "PF": "206",
        "PTS": "313"
    },
    {
        "Rk": "34",
        "Player": "Rollen Hans",
        "Pos": "SG",
        "Age": "23",
        "Tm": "BLB",
        "G": "13",
        "GS": "",
        "MP": "178",
        "FG": "30",
        "FGA": "67",
        "FG%": ".448",
        "3P": "",
        "3PA": "",
        "3P%": "",
        "2P": "30",
        "2PA": "67",
        "2P%": ".448",
        "eFG%": ".448",
        "FT": "13",
        "FTA": "25",
        "FT%": ".520",
        "ORB": "",
        "DRB": "",
        "TRB": "16",
        "AST": "26",
        "STL": "",
        "BLK": "",
        "TOV": "",
        "PF": "20",
        "PTS": "73"
    },
    {
        "Rk": "35",
        "Player": "Bob Harrison",
        "Pos": "PG",
        "Age": "27",
        "Tm": "MLH",
        "G": "72",
        "GS": "",
        "MP": "2300",
        "FG": "299",
        "FGA": "875",
        "FG%": ".342",
        "3P": "",
        "3PA": "",
        "3P%": "",
        "2P": "299",
        "2PA": "875",
        "2P%": ".342",
        "eFG%": ".342",
        "FT": "126",
        "FTA": "185",
        "FT%": ".681",
        "ORB": "",
        "DRB": "",
        "TRB": "226",
        "AST": "252",
        "STL": "",
        "BLK": "",
        "TOV": "",
        "PF": "291",
        "PTS": "724"
    },
    {
        "Rk": "36",
        "Player": "Herm Hedderick",
        "Pos": "G",
        "Age": "25",
        "Tm": "NYK",
        "G": "5",
        "GS": "",
        "MP": "23",
        "FG": "2",
        "FGA": "9",
        "FG%": ".222",
        "3P": "",
        "3PA": "",
        "3P%": "",
        "2P": "2",
        "2PA": "9",
        "2P%": ".222",
        "eFG%": ".222",
        "FT": "0",
        "FTA": "1",
        "FT%": ".000",
        "ORB": "",
        "DRB": "",
        "TRB": "4",
        "AST": "2",
        "STL": "",
        "BLK": "",
        "TOV": "",
        "PF": "3",
        "PTS": "4"
    },
    {
        "Rk": "37",
        "Player": "Don Henriksen",
        "Pos": "PF",
        "Age": "25",
        "Tm": "TOT",
        "G": "70",
        "GS": "",
        "MP": "1664",
        "FG": "139",
        "FGA": "406",
        "FG%": ".342",
        "3P": "",
        "3PA": "",
        "3P%": "",
        "2P": "139",
        "2PA": "406",
        "2P%": ".342",
        "eFG%": ".342",
        "FT": "137",
        "FTA": "195",
        "FT%": ".703",
        "ORB": "",
        "DRB": "",
        "TRB": "484",
        "AST": "111",
        "STL": "",
        "BLK": "",
        "TOV": "",
        "PF": "190",
        "PTS": "415"
    },
    {
        "Rk": "37",
        "Player": "Don Henriksen",
        "Pos": "F-C",
        "Age": "25",
        "Tm": "BLB",
        "G": "14",
        "GS": "",
        "MP": "429",
        "FG": "28",
        "FGA": "91",
        "FG%": ".308",
        "3P": "",
        "3PA": "",
        "3P%": "",
        "2P": "28",
        "2PA": "91",
        "2P%": ".308",
        "eFG%": ".308",
        "FT": "51",
        "FTA": "65",
        "FT%": ".785",
        "ORB": "",
        "DRB": "",
        "TRB": "49",
        "AST": "32",
        "STL": "",
        "BLK": "",
        "TOV": "",
        "PF": "42",
        "PTS": "107"
    },
    {
        "Rk": "37",
        "Player": "Don Henriksen",
        "Pos": "PF",
        "Age": "25",
        "Tm": "ROC",
        "G": "56",
        "GS": "",
        "MP": "1235",
        "FG": "111",
        "FGA": "315",
        "FG%": ".352",
        "3P": "",
        "3PA": "",
        "3P%": "",
        "2P": "111",
        "2PA": "315",
        "2P%": ".352",
        "eFG%": ".352",
        "FT": "86",
        "FTA": "130",
        "FT%": ".662",
        "ORB": "",
        "DRB": "",
        "TRB": "435",
        "AST": "79",
        "STL": "",
        "BLK": "",
        "TOV": "",
        "PF": "148",
        "PTS": "308"
    },
    {
        "Rk": "38",
        "Player": "Lew Hitch",
        "Pos": "F-C",
        "Age": "25",
        "Tm": "TOT",
        "G": "74",
        "GS": "",
        "MP": "1774",
        "FG": "167",
        "FGA": "417",
        "FG%": ".400",
        "3P": "",
        "3PA": "",
        "3P%": "",
        "2P": "167",
        "2PA": "417",
        "2P%": ".400",
        "eFG%": ".400",
        "FT": "115",
        "FTA": "169",
        "FT%": ".680",
        "ORB": "",
        "DRB": "",
        "TRB": "438",
        "AST": "125",
        "STL": "",
        "BLK": "",
        "TOV": "",
        "PF": "110",
        "PTS": "449"
    },
    {
        "Rk": "39",
        "Player": "Paul Hoffman",
        "Pos": "G-F",
        "Age": "29",
        "Tm": "TOT",
        "G": "38",
        "GS": "",
        "MP": "670",
        "FG": "65",
        "FGA": "216",
        "FG%": ".301",
        "3P": "",
        "3PA": "",
        "3P%": "",
        "2P": "65",
        "2PA": "216",
        "2P%": ".301",
        "eFG%": ".301",
        "FT": "64",
        "FTA": "93",
        "FT%": ".688",
        "ORB": "",
        "DRB": "",
        "TRB": "124",
        "AST": "94",
        "STL": "",
        "BLK": "",
        "TOV": "",
        "PF": "93",
        "PTS": "194"
    },
    {
        "Rk": "40",
        "Player": "Jim Holstein",
        "Pos": "SF",
        "Age": "24",
        "Tm": "MNL",
        "G": "62",
        "GS": "",
        "MP": "980",
        "FG": "107",
        "FGA": "330",
        "FG%": ".324",
        "3P": "",
        "3PA": "",
        "3P%": "",
        "2P": "107",
        "2PA": "330",
        "2P%": ".324",
        "eFG%": ".324",
        "FT": "67",
        "FTA": "94",
        "FT%": ".713",
        "ORB": "",
        "DRB": "",
        "TRB": "206",
        "AST": "58",
        "STL": "",
        "BLK": "",
        "TOV": "",
        "PF": "107",
        "PTS": "281"
    },
    {
        "Rk": "Rk",
        "Player": "Player",
        "Pos": "Pos",
        "Age": "Age",
        "Tm": "Tm",
        "G": "G",
        "GS": "GS",
        "MP": "MP",
        "FG": "FG",
        "FGA": "FGA",
        "FG%": "FG%",
        "3P": "3P",
        "3PA": "3PA",
        "3P%": "3P%",
        "2P": "2P",
        "2PA": "2PA",
        "2P%": "2P%",
        "eFG%": "eFG%",
        "FT": "FT",
        "FTA": "FTA",
        "FT%": "FT%",
        "ORB": "ORB",
        "DRB": "DRB",
        "TRB": "TRB",
        "AST": "AST",
        "STL": "STL",
        "BLK": "BLK",
        "TOV": "TOV",
        "PF": "PF",
        "PTS": "PTS"
    },
    {
        "Rk": "41",
        "Player": "Bob Houbregs*",
        "Pos": "C-F",
        "Age": "22",
        "Tm": "TOT",
        "G": "64",
        "GS": "",
        "MP": "1326",
        "FG": "148",
        "FGA": "386",
        "FG%": ".383",
        "3P": "",
        "3PA": "",
        "3P%": "",
        "2P": "148",
        "2PA": "386",
        "2P%": ".383",
        "eFG%": ".383",
        "FT": "129",
        "FTA": "182",
        "FT%": ".709",
        "ORB": "",
        "DRB": "",
        "TRB": "297",
        "AST": "86",
        "STL": "",
        "BLK": "",
        "TOV": "",
        "PF": "180",
        "PTS": "425"
    },
    {
        "Rk": "42",
        "Player": "Mel Hutchins",
        "Pos": "PF",
        "Age": "26",
        "Tm": "FTW",
        "G": "72",
        "GS": "",
        "MP": "2860",
        "FG": "341",
        "FGA": "903",
        "FG%": ".378",
        "3P": "",
        "3PA": "",
        "3P%": "",
        "2P": "341",
        "2PA": "903",
        "2P%": ".378",
        "eFG%": ".378",
        "FT": "182",
        "FTA": "257",
        "FT%": ".708",
        "ORB": "",
        "DRB": "",
        "TRB": "665",
        "AST": "247",
        "STL": "",
        "BLK": "",
        "TOV": "",
        "PF": "232",
        "PTS": "864"
    },
    {
        "Rk": "43",
        "Player": "Neil Johnston*",
        "Pos": "C",
        "Age": "25",
        "Tm": "PHW",
        "G": "72",
        "GS": "",
        "MP": "2917",
        "FG": "521",
        "FGA": "1184",
        "FG%": ".440",
        "3P": "",
        "3PA": "",
        "3P%": "",
        "2P": "521",
        "2PA": "1184",
        "2P%": ".440",
        "eFG%": ".440",
        "FT": "589",
        "FTA": "769",
        "FT%": ".766",
        "ORB": "",
        "DRB": "",
        "TRB": "1085",
        "AST": "215",
        "STL": "",
        "BLK": "",
        "TOV": "",
        "PF": "255",
        "PTS": "1631"
    },
    {
        "Rk": "44",
        "Player": "Ed Kalafat",
        "Pos": "PF",
        "Age": "22",
        "Tm": "MNL",
        "G": "72",
        "GS": "",
        "MP": "1102",
        "FG": "118",
        "FGA": "375",
        "FG%": ".315",
        "3P": "",
        "3PA": "",
        "3P%": "",
        "2P": "118",
        "2PA": "375",
        "2P%": ".315",
        "eFG%": ".315",
        "FT": "111",
        "FTA": "168",
        "FT%": ".661",
        "ORB": "",
        "DRB": "",
        "TRB": "317",
        "AST": "75",
        "STL": "",
        "BLK": "",
        "TOV": "",
        "PF": "205",
        "PTS": "347"
    },
    {
        "Rk": "45",
        "Player": "Mike Kearns",
        "Pos": "PG",
        "Age": "25",
        "Tm": "PHW",
        "G": "6",
        "GS": "",
        "MP": "25",
        "FG": "0",
        "FGA": "5",
        "FG%": ".000",
        "3P": "",
        "3PA": "",
        "3P%": "",
        "2P": "0",
        "2PA": "5",
        "2P%": ".000",
        "eFG%": ".000",
        "FT": "1",
        "FTA": "4",
        "FT%": ".250",
        "ORB": "",
        "DRB": "",
        "TRB": "3",
        "AST": "5",
        "STL": "",
        "BLK": "",
        "TOV": "",
        "PF": "1",
        "PTS": "1"
    },
    {
        "Rk": "46",
        "Player": "Billy Kenville",
        "Pos": "SG",
        "Age": "24",
        "Tm": "SYR",
        "G": "70",
        "GS": "",
        "MP": "1380",
        "FG": "172",
        "FGA": "482",
        "FG%": ".357",
        "3P": "",
        "3PA": "",
        "3P%": "",
        "2P": "172",
        "2PA": "482",
        "2P%": ".357",
        "eFG%": ".357",
        "FT": "154",
        "FTA": "201",
        "FT%": ".766",
        "ORB": "",
        "DRB": "",
        "TRB": "247",
        "AST": "150",
        "STL": "",
        "BLK": "",
        "TOV": "",
        "PF": "132",
        "PTS": "498"
    },
    {
        "Rk": "47",
        "Player": "Red Kerr",
        "Pos": "C",
        "Age": "22",
        "Tm": "SYR",
        "G": "72",
        "GS": "",
        "MP": "1529",
        "FG": "301",
        "FGA": "718",
        "FG%": ".419",
        "3P": "",
        "3PA": "",
        "3P%": "",
        "2P": "301",
        "2PA": "718",
        "2P%": ".419",
        "eFG%": ".419",
        "FT": "152",
        "FTA": "223",
        "FT%": ".682",
        "ORB": "",
        "DRB": "",
        "TRB": "474",
        "AST": "80",
        "STL": "",
        "BLK": "",
        "TOV": "",
        "PF": "165",
        "PTS": "754"
    },
    {
        "Rk": "48",
        "Player": "Dan King",
        "Pos": "F",
        "Age": "24",
        "Tm": "BLB",
        "G": "12",
        "GS": "",
        "MP": "103",
        "FG": "7",
        "FGA": "22",
        "FG%": ".318",
        "3P": "",
        "3PA": "",
        "3P%": "",
        "2P": "7",
        "2PA": "22",
        "2P%": ".318",
        "eFG%": ".318",
        "FT": "5",
        "FTA": "10",
        "FT%": ".500",
        "ORB": "",
        "DRB": "",
        "TRB": "25",
        "AST": "3",
        "STL": "",
        "BLK": "",
        "TOV": "",
        "PF": "5",
        "PTS": "19"
    },
    {
        "Rk": "49",
        "Player": "George King",
        "Pos": "PG",
        "Age": "26",
        "Tm": "SYR",
        "G": "67",
        "GS": "",
        "MP": "2015",
        "FG": "228",
        "FGA": "605",
        "FG%": ".377",
        "3P": "",
        "3PA": "",
        "3P%": "",
        "2P": "228",
        "2PA": "605",
        "2P%": ".377",
        "eFG%": ".377",
        "FT": "140",
        "FTA": "229",
        "FT%": ".611",
        "ORB": "",
        "DRB": "",
        "TRB": "227",
        "AST": "331",
        "STL": "",
        "BLK": "",
        "TOV": "",
        "PF": "148",
        "PTS": "596"
    },
    {
        "Rk": "50",
        "Player": "Bob Knight",
        "Pos": "G-F",
        "Age": "25",
        "Tm": "NYK",
        "G": "2",
        "GS": "",
        "MP": "29",
        "FG": "3",
        "FGA": "7",
        "FG%": ".429",
        "3P": "",
        "3PA": "",
        "3P%": "",
        "2P": "3",
        "2PA": "7",
        "2P%": ".429",
        "eFG%": ".429",
        "FT": "1",
        "FTA": "1",
        "FT%": "1.000",
        "ORB": "",
        "DRB": "",
        "TRB": "1",
        "AST": "8",
        "STL": "",
        "BLK": "",
        "TOV": "",
        "PF": "6",
        "PTS": "7"
    },
    {
        "Rk": "51",
        "Player": "Earl Lloyd*",
        "Pos": "SF",
        "Age": "26",
        "Tm": "SYR",
        "G": "72",
        "GS": "",
        "MP": "2212",
        "FG": "286",
        "FGA": "784",
        "FG%": ".365",
        "3P": "",
        "3PA": "",
        "3P%": "",
        "2P": "286",
        "2PA": "784",
        "2P%": ".365",
        "eFG%": ".365",
        "FT": "159",
        "FTA": "212",
        "FT%": ".750",
        "ORB": "",
        "DRB": "",
        "TRB": "553",
        "AST": "151",
        "STL": "",
        "BLK": "",
        "TOV": "",
        "PF": "283",
        "PTS": "731"
    },
    {
        "Rk": "52",
        "Player": "Clyde Lovellette*",
        "Pos": "C",
        "Age": "25",
        "Tm": "MNL",
        "G": "70",
        "GS": "",
        "MP": "2361",
        "FG": "519",
        "FGA": "1192",
        "FG%": ".435",
        "3P": "",
        "3PA": "",
        "3P%": "",
        "2P": "519",
        "2PA": "1192",
        "2P%": ".435",
        "eFG%": ".435",
        "FT": "273",
        "FTA": "398",
        "FT%": ".686",
        "ORB": "",
        "DRB": "",
        "TRB": "802",
        "AST": "100",
        "STL": "",
        "BLK": "",
        "TOV": "",
        "PF": "262",
        "PTS": "1311"
    },
    {
        "Rk": "53",
        "Player": "Ed Macauley*",
        "Pos": "C",
        "Age": "26",
        "Tm": "BOS",
        "G": "71",
        "GS": "",
        "MP": "2706",
        "FG": "403",
        "FGA": "951",
        "FG%": ".424",
        "3P": "",
        "3PA": "",
        "3P%": "",
        "2P": "403",
        "2PA": "951",
        "2P%": ".424",
        "eFG%": ".424",
        "FT": "442",
        "FTA": "558",
        "FT%": ".792",
        "ORB": "",
        "DRB": "",
        "TRB": "600",
        "AST": "275",
        "STL": "",
        "BLK": "",
        "TOV": "",
        "PF": "171",
        "PTS": "1248"
    },
    {
        "Rk": "54",
        "Player": "Ronnie MacGilvray",
        "Pos": "PG",
        "Age": "24",
        "Tm": "MLH",
        "G": "6",
        "GS": "",
        "MP": "57",
        "FG": "2",
        "FGA": "12",
        "FG%": ".167",
        "3P": "",
        "3PA": "",
        "3P%": "",
        "2P": "2",
        "2PA": "12",
        "2P%": ".167",
        "eFG%": ".167",
        "FT": "4",
        "FTA": "7",
        "FT%": ".571",
        "ORB": "",
        "DRB": "",
        "TRB": "9",
        "AST": "11",
        "STL": "",
        "BLK": "",
        "TOV": "",
        "PF": "5",
        "PTS": "8"
    },
    {
        "Rk": "55",
        "Player": "Tom Marshall",
        "Pos": "SF",
        "Age": "24",
        "Tm": "ROC",
        "G": "72",
        "GS": "",
        "MP": "1337",
        "FG": "223",
        "FGA": "505",
        "FG%": ".442",
        "3P": "",
        "3PA": "",
        "3P%": "",
        "2P": "223",
        "2PA": "505",
        "2P%": ".442",
        "eFG%": ".442",
        "FT": "131",
        "FTA": "194",
        "FT%": ".675",
        "ORB": "",
        "DRB": "",
        "TRB": "256",
        "AST": "111",
        "STL": "",
        "BLK": "",
        "TOV": "",
        "PF": "99",
        "PTS": "577"
    },
    {
        "Rk": "56",
        "Player": "Phil Martin",
        "Pos": "SF",
        "Age": "26",
        "Tm": "MLH",
        "G": "7",
        "GS": "",
        "MP": "47",
        "FG": "5",
        "FGA": "19",
        "FG%": ".263",
        "3P": "",
        "3PA": "",
        "3P%": "",
        "2P": "5",
        "2PA": "19",
        "2P%": ".263",
        "eFG%": ".263",
        "FT": "2",
        "FTA": "2",
        "FT%": "1.000",
        "ORB": "",
        "DRB": "",
        "TRB": "10",
        "AST": "6",
        "STL": "",
        "BLK": "",
        "TOV": "",
        "PF": "7",
        "PTS": "12"
    },
    {
        "Rk": "57",
        "Player": "Slater Martin*",
        "Pos": "PG",
        "Age": "29",
        "Tm": "MNL",
        "G": "72",
        "GS": "",
        "MP": "2784",
        "FG": "350",
        "FGA": "919",
        "FG%": ".381",
        "3P": "",
        "3PA": "",
        "3P%": "",
        "2P": "350",
        "2PA": "919",
        "2P%": ".381",
        "eFG%": ".381",
        "FT": "276",
        "FTA": "359",
        "FT%": ".769",
        "ORB": "",
        "DRB": "",
        "TRB": "260",
        "AST": "427",
        "STL": "",
        "BLK": "",
        "TOV": "",
        "PF": "221",
        "PTS": "976"
    },
    {
        "Rk": "58",
        "Player": "Ken McBride",
        "Pos": "SG",
        "Age": "",
        "Tm": "MLH",
        "G": "12",
        "GS": "",
        "MP": "249",
        "FG": "48",
        "FGA": "147",
        "FG%": ".327",
        "3P": "",
        "3PA": "",
        "3P%": "",
        "2P": "48",
        "2PA": "147",
        "2P%": ".327",
        "eFG%": ".327",
        "FT": "21",
        "FTA": "29",
        "FT%": ".724",
        "ORB": "",
        "DRB": "",
        "TRB": "31",
        "AST": "14",
        "STL": "",
        "BLK": "",
        "TOV": "",
        "PF": "31",
        "PTS": "117"
    },
    {
        "Rk": "59",
        "Player": "Alfred McGuire*",
        "Pos": "PG",
        "Age": "26",
        "Tm": "BLB",
        "G": "10",
        "GS": "",
        "MP": "98",
        "FG": "9",
        "FGA": "32",
        "FG%": ".281",
        "3P": "",
        "3PA": "",
        "3P%": "",
        "2P": "9",
        "2PA": "32",
        "2P%": ".281",
        "eFG%": ".281",
        "FT": "5",
        "FTA": "7",
        "FT%": ".714",
        "ORB": "",
        "DRB": "",
        "TRB": "9",
        "AST": "8",
        "STL": "",
        "BLK": "",
        "TOV": "",
        "PF": "15",
        "PTS": "23"
    },
    {
        "Rk": "60",
        "Player": "Dick McGuire*",
        "Pos": "PG",
        "Age": "29",
        "Tm": "NYK",
        "G": "71",
        "GS": "",
        "MP": "2310",
        "FG": "226",
        "FGA": "581",
        "FG%": ".389",
        "3P": "",
        "3PA": "",
        "3P%": "",
        "2P": "226",
        "2PA": "581",
        "2P%": ".389",
        "eFG%": ".389",
        "FT": "195",
        "FTA": "303",
        "FT%": ".644",
        "ORB": "",
        "DRB": "",
        "TRB": "322",
        "AST": "542",
        "STL": "",
        "BLK": "",
        "TOV": "",
        "PF": "143",
        "PTS": "647"
    },
    {
        "Rk": "Rk",
        "Player": "Player",
        "Pos": "Pos",
        "Age": "Age",
        "Tm": "Tm",
        "G": "G",
        "GS": "GS",
        "MP": "MP",
        "FG": "FG",
        "FGA": "FGA",
        "FG%": "FG%",
        "3P": "3P",
        "3PA": "3PA",
        "3P%": "3P%",
        "2P": "2P",
        "2PA": "2PA",
        "2P%": "2P%",
        "eFG%": "eFG%",
        "FT": "FT",
        "FTA": "FTA",
        "FT%": "FT%",
        "ORB": "ORB",
        "DRB": "DRB",
        "TRB": "TRB",
        "AST": "AST",
        "STL": "STL",
        "BLK": "BLK",
        "TOV": "TOV",
        "PF": "PF",
        "PTS": "PTS"
    },
    {
        "Rk": "61",
        "Player": "Jack McMahon",
        "Pos": "PG",
        "Age": "26",
        "Tm": "ROC",
        "G": "72",
        "GS": "",
        "MP": "1807",
        "FG": "251",
        "FGA": "721",
        "FG%": ".348",
        "3P": "",
        "3PA": "",
        "3P%": "",
        "2P": "251",
        "2PA": "721",
        "2P%": ".348",
        "eFG%": ".348",
        "FT": "143",
        "FTA": "225",
        "FT%": ".636",
        "ORB": "",
        "DRB": "",
        "TRB": "211",
        "AST": "246",
        "STL": "",
        "BLK": "",
        "TOV": "",
        "PF": "179",
        "PTS": "645"
    },
    {
        "Rk": "62",
        "Player": "Carl McNulty",
        "Pos": "SG",
        "Age": "24",
        "Tm": "MLH",
        "G": "1",
        "GS": "",
        "MP": "14",
        "FG": "1",
        "FGA": "6",
        "FG%": ".167",
        "3P": "",
        "3PA": "",
        "3P%": "",
        "2P": "1",
        "2PA": "6",
        "2P%": ".167",
        "eFG%": ".167",
        "FT": "0",
        "FTA": "0",
        "FT%": "",
        "ORB": "",
        "DRB": "",
        "TRB": "0",
        "AST": "0",
        "STL": "",
        "BLK": "",
        "TOV": "",
        "PF": "1",
        "PTS": "2"
    },
    {
        "Rk": "63",
        "Player": "Monk Meineke",
        "Pos": "PF",
        "Age": "24",
        "Tm": "FTW",
        "G": "68",
        "GS": "",
        "MP": "1026",
        "FG": "136",
        "FGA": "366",
        "FG%": ".372",
        "3P": "",
        "3PA": "",
        "3P%": "",
        "2P": "136",
        "2PA": "366",
        "2P%": ".372",
        "eFG%": ".372",
        "FT": "119",
        "FTA": "170",
        "FT%": ".700",
        "ORB": "",
        "DRB": "",
        "TRB": "246",
        "AST": "64",
        "STL": "",
        "BLK": "",
        "TOV": "",
        "PF": "153",
        "PTS": "391"
    },
    {
        "Rk": "64",
        "Player": "Vern Mikkelsen*",
        "Pos": "PF",
        "Age": "26",
        "Tm": "MNL",
        "G": "71",
        "GS": "",
        "MP": "2559",
        "FG": "440",
        "FGA": "1043",
        "FG%": ".422",
        "3P": "",
        "3PA": "",
        "3P%": "",
        "2P": "440",
        "2PA": "1043",
        "2P%": ".422",
        "eFG%": ".422",
        "FT": "447",
        "FTA": "598",
        "FT%": ".747",
        "ORB": "",
        "DRB": "",
        "TRB": "722",
        "AST": "145",
        "STL": "",
        "BLK": "",
        "TOV": "",
        "PF": "319",
        "PTS": "1327"
    },
    {
        "Rk": "65",
        "Player": "Jackie Moore",
        "Pos": "F",
        "Age": "22",
        "Tm": "TOT",
        "G": "23",
        "GS": "",
        "MP": "376",
        "FG": "44",
        "FGA": "115",
        "FG%": ".383",
        "3P": "",
        "3PA": "",
        "3P%": "",
        "2P": "44",
        "2PA": "115",
        "2P%": ".383",
        "eFG%": ".383",
        "FT": "22",
        "FTA": "47",
        "FT%": ".468",
        "ORB": "",
        "DRB": "",
        "TRB": "105",
        "AST": "20",
        "STL": "",
        "BLK": "",
        "TOV": "",
        "PF": "62",
        "PTS": "110"
    },
    {
        "Rk": "66",
        "Player": "Red Morrison",
        "Pos": "C",
        "Age": "22",
        "Tm": "BOS",
        "G": "71",
        "GS": "",
        "MP": "1227",
        "FG": "120",
        "FGA": "284",
        "FG%": ".423",
        "3P": "",
        "3PA": "",
        "3P%": "",
        "2P": "120",
        "2PA": "284",
        "2P%": ".423",
        "eFG%": ".423",
        "FT": "72",
        "FTA": "115",
        "FT%": ".626",
        "ORB": "",
        "DRB": "",
        "TRB": "451",
        "AST": "82",
        "STL": "",
        "BLK": "",
        "TOV": "",
        "PF": "222",
        "PTS": "312"
    },
    {
        "Rk": "67",
        "Player": "Ken Murray",
        "Pos": "G-F",
        "Age": "26",
        "Tm": "TOT",
        "G": "66",
        "GS": "",
        "MP": "1590",
        "FG": "187",
        "FGA": "535",
        "FG%": ".350",
        "3P": "",
        "3PA": "",
        "3P%": "",
        "2P": "187",
        "2PA": "535",
        "2P%": ".350",
        "eFG%": ".350",
        "FT": "98",
        "FTA": "129",
        "FT%": ".760",
        "ORB": "",
        "DRB": "",
        "TRB": "179",
        "AST": "224",
        "STL": "",
        "BLK": "",
        "TOV": "",
        "PF": "126",
        "PTS": "472"
    },
    {
        "Rk": "68",
        "Player": "Boris Nachamkin",
        "Pos": "F",
        "Age": "21",
        "Tm": "ROC",
        "G": "6",
        "GS": "",
        "MP": "59",
        "FG": "6",
        "FGA": "20",
        "FG%": ".300",
        "3P": "",
        "3PA": "",
        "3P%": "",
        "2P": "6",
        "2PA": "20",
        "2P%": ".300",
        "eFG%": ".300",
        "FT": "8",
        "FTA": "13",
        "FT%": ".615",
        "ORB": "",
        "DRB": "",
        "TRB": "19",
        "AST": "3",
        "STL": "",
        "BLK": "",
        "TOV": "",
        "PF": "6",
        "PTS": "20"
    },
    {
        "Rk": "69",
        "Player": "Jim Neal",
        "Pos": "C",
        "Age": "24",
        "Tm": "BLB",
        "G": "13",
        "GS": "",
        "MP": "194",
        "FG": "12",
        "FGA": "59",
        "FG%": ".203",
        "3P": "",
        "3PA": "",
        "3P%": "",
        "2P": "12",
        "2PA": "59",
        "2P%": ".203",
        "eFG%": ".203",
        "FT": "14",
        "FTA": "21",
        "FT%": ".667",
        "ORB": "",
        "DRB": "",
        "TRB": "47",
        "AST": "9",
        "STL": "",
        "BLK": "",
        "TOV": "",
        "PF": "22",
        "PTS": "38"
    },
    {
        "Rk": "70",
        "Player": "Jack Nichols",
        "Pos": "PF",
        "Age": "28",
        "Tm": "BOS",
        "G": "64",
        "GS": "",
        "MP": "1910",
        "FG": "249",
        "FGA": "656",
        "FG%": ".380",
        "3P": "",
        "3PA": "",
        "3P%": "",
        "2P": "249",
        "2PA": "656",
        "2P%": ".380",
        "eFG%": ".380",
        "FT": "138",
        "FTA": "177",
        "FT%": ".780",
        "ORB": "",
        "DRB": "",
        "TRB": "533",
        "AST": "144",
        "STL": "",
        "BLK": "",
        "TOV": "",
        "PF": "238",
        "PTS": "636"
    },
    {
        "Rk": "71",
        "Player": "Wally Osterkorn",
        "Pos": "SF",
        "Age": "26",
        "Tm": "SYR",
        "G": "19",
        "GS": "",
        "MP": "286",
        "FG": "20",
        "FGA": "97",
        "FG%": ".206",
        "3P": "",
        "3PA": "",
        "3P%": "",
        "2P": "20",
        "2PA": "97",
        "2P%": ".206",
        "eFG%": ".206",
        "FT": "16",
        "FTA": "32",
        "FT%": ".500",
        "ORB": "",
        "DRB": "",
        "TRB": "70",
        "AST": "17",
        "STL": "",
        "BLK": "",
        "TOV": "",
        "PF": "32",
        "PTS": "56"
    },
    {
        "Rk": "72",
        "Player": "Togo Palazzi",
        "Pos": "SG",
        "Age": "22",
        "Tm": "BOS",
        "G": "53",
        "GS": "",
        "MP": "504",
        "FG": "101",
        "FGA": "253",
        "FG%": ".399",
        "3P": "",
        "3PA": "",
        "3P%": "",
        "2P": "101",
        "2PA": "253",
        "2P%": ".399",
        "eFG%": ".399",
        "FT": "45",
        "FTA": "60",
        "FT%": ".750",
        "ORB": "",
        "DRB": "",
        "TRB": "146",
        "AST": "30",
        "STL": "",
        "BLK": "",
        "TOV": "",
        "PF": "60",
        "PTS": "247"
    },
    {
        "Rk": "73",
        "Player": "Bob Peterson",
        "Pos": "PF",
        "Age": "23",
        "Tm": "NYK",
        "G": "37",
        "GS": "",
        "MP": "503",
        "FG": "62",
        "FGA": "169",
        "FG%": ".367",
        "3P": "",
        "3PA": "",
        "3P%": "",
        "2P": "62",
        "2PA": "169",
        "2P%": ".367",
        "eFG%": ".367",
        "FT": "30",
        "FTA": "45",
        "FT%": ".667",
        "ORB": "",
        "DRB": "",
        "TRB": "154",
        "AST": "31",
        "STL": "",
        "BLK": "",
        "TOV": "",
        "PF": "80",
        "PTS": "154"
    },
    {
        "Rk": "74",
        "Player": "Bob Pettit*",
        "Pos": "PF",
        "Age": "22",
        "Tm": "MLH",
        "G": "72",
        "GS": "",
        "MP": "2659",
        "FG": "520",
        "FGA": "1279",
        "FG%": ".407",
        "3P": "",
        "3PA": "",
        "3P%": "",
        "2P": "520",
        "2PA": "1279",
        "2P%": ".407",
        "eFG%": ".407",
        "FT": "426",
        "FTA": "567",
        "FT%": ".751",
        "ORB": "",
        "DRB": "",
        "TRB": "994",
        "AST": "229",
        "STL": "",
        "BLK": "",
        "TOV": "",
        "PF": "258",
        "PTS": "1466"
    },
    {
        "Rk": "75",
        "Player": "Andy Phillip*",
        "Pos": "PG",
        "Age": "32",
        "Tm": "FTW",
        "G": "64",
        "GS": "",
        "MP": "2332",
        "FG": "202",
        "FGA": "545",
        "FG%": ".371",
        "3P": "",
        "3PA": "",
        "3P%": "",
        "2P": "202",
        "2PA": "545",
        "2P%": ".371",
        "eFG%": ".371",
        "FT": "213",
        "FTA": "308",
        "FT%": ".692",
        "ORB": "",
        "DRB": "",
        "TRB": "290",
        "AST": "491",
        "STL": "",
        "BLK": "",
        "TOV": "",
        "PF": "166",
        "PTS": "617"
    },
    {
        "Rk": "76",
        "Player": "Jim Pollard*",
        "Pos": "SF",
        "Age": "32",
        "Tm": "MNL",
        "G": "63",
        "GS": "",
        "MP": "1960",
        "FG": "265",
        "FGA": "749",
        "FG%": ".354",
        "3P": "",
        "3PA": "",
        "3P%": "",
        "2P": "265",
        "2PA": "749",
        "2P%": ".354",
        "eFG%": ".354",
        "FT": "151",
        "FTA": "186",
        "FT%": ".812",
        "ORB": "",
        "DRB": "",
        "TRB": "458",
        "AST": "160",
        "STL": "",
        "BLK": "",
        "TOV": "",
        "PF": "147",
        "PTS": "681"
    },
    {
        "Rk": "77",
        "Player": "Frank Ramsey*",
        "Pos": "SF",
        "Age": "23",
        "Tm": "BOS",
        "G": "64",
        "GS": "",
        "MP": "1754",
        "FG": "236",
        "FGA": "592",
        "FG%": ".399",
        "3P": "",
        "3PA": "",
        "3P%": "",
        "2P": "236",
        "2PA": "592",
        "2P%": ".399",
        "eFG%": ".399",
        "FT": "243",
        "FTA": "322",
        "FT%": ".755",
        "ORB": "",
        "DRB": "",
        "TRB": "402",
        "AST": "185",
        "STL": "",
        "BLK": "",
        "TOV": "",
        "PF": "250",
        "PTS": "715"
    },
    {
        "Rk": "78",
        "Player": "George Ratkovicz",
        "Pos": "PF",
        "Age": "32",
        "Tm": "MLH",
        "G": "9",
        "GS": "",
        "MP": "102",
        "FG": "3",
        "FGA": "19",
        "FG%": ".158",
        "3P": "",
        "3PA": "",
        "3P%": "",
        "2P": "3",
        "2PA": "19",
        "2P%": ".158",
        "eFG%": ".158",
        "FT": "10",
        "FTA": "23",
        "FT%": ".435",
        "ORB": "",
        "DRB": "",
        "TRB": "17",
        "AST": "13",
        "STL": "",
        "BLK": "",
        "TOV": "",
        "PF": "15",
        "PTS": "16"
    },
    {
        "Rk": "79",
        "Player": "Arnie Risen*",
        "Pos": "C",
        "Age": "30",
        "Tm": "ROC",
        "G": "69",
        "GS": "",
        "MP": "1970",
        "FG": "259",
        "FGA": "699",
        "FG%": ".371",
        "3P": "",
        "3PA": "",
        "3P%": "",
        "2P": "259",
        "2PA": "699",
        "2P%": ".371",
        "eFG%": ".371",
        "FT": "279",
        "FTA": "375",
        "FT%": ".744",
        "ORB": "",
        "DRB": "",
        "TRB": "703",
        "AST": "112",
        "STL": "",
        "BLK": "",
        "TOV": "",
        "PF": "253",
        "PTS": "797"
    },
    {
        "Rk": "80",
        "Player": "Red Rocha",
        "Pos": "C",
        "Age": "31",
        "Tm": "SYR",
        "G": "72",
        "GS": "",
        "MP": "2473",
        "FG": "295",
        "FGA": "801",
        "FG%": ".368",
        "3P": "",
        "3PA": "",
        "3P%": "",
        "2P": "295",
        "2PA": "801",
        "2P%": ".368",
        "eFG%": ".368",
        "FT": "222",
        "FTA": "284",
        "FT%": ".782",
        "ORB": "",
        "DRB": "",
        "TRB": "489",
        "AST": "178",
        "STL": "",
        "BLK": "",
        "TOV": "",
        "PF": "242",
        "PTS": "812"
    },
    {
        "Rk": "Rk",
        "Player": "Player",
        "Pos": "Pos",
        "Age": "Age",
        "Tm": "Tm",
        "G": "G",
        "GS": "GS",
        "MP": "MP",
        "FG": "FG",
        "FGA": "FGA",
        "FG%": "FG%",
        "3P": "3P",
        "3PA": "3PA",
        "3P%": "3P%",
        "2P": "2P",
        "2PA": "2PA",
        "2P%": "2P%",
        "eFG%": "eFG%",
        "FT": "FT",
        "FTA": "FTA",
        "FT%": "FT%",
        "ORB": "ORB",
        "DRB": "DRB",
        "TRB": "TRB",
        "AST": "AST",
        "STL": "STL",
        "BLK": "BLK",
        "TOV": "TOV",
        "PF": "PF",
        "PTS": "PTS"
    },
    {
        "Rk": "81",
        "Player": "Al Roges",
        "Pos": "G-F",
        "Age": "24",
        "Tm": "TOT",
        "G": "17",
        "GS": "",
        "MP": "201",
        "FG": "23",
        "FGA": "61",
        "FG%": ".377",
        "3P": "",
        "3PA": "",
        "3P%": "",
        "2P": "23",
        "2PA": "61",
        "2P%": ".377",
        "eFG%": ".377",
        "FT": "15",
        "FTA": "24",
        "FT%": ".625",
        "ORB": "",
        "DRB": "",
        "TRB": "24",
        "AST": "19",
        "STL": "",
        "BLK": "",
        "TOV": "",
        "PF": "20",
        "PTS": "61"
    },
    {
        "Rk": "82",
        "Player": "Dick Rosenthal",
        "Pos": "SF",
        "Age": "25",
        "Tm": "FTW",
        "G": "67",
        "GS": "",
        "MP": "1406",
        "FG": "197",
        "FGA": "523",
        "FG%": ".377",
        "3P": "",
        "3PA": "",
        "3P%": "",
        "2P": "197",
        "2PA": "523",
        "2P%": ".377",
        "eFG%": ".377",
        "FT": "130",
        "FTA": "181",
        "FT%": ".718",
        "ORB": "",
        "DRB": "",
        "TRB": "300",
        "AST": "153",
        "STL": "",
        "BLK": "",
        "TOV": "",
        "PF": "179",
        "PTS": "524"
    },
    {
        "Rk": "83",
        "Player": "Pep Saul",
        "Pos": "SG",
        "Age": "30",
        "Tm": "MLH",
        "G": "65",
        "GS": "",
        "MP": "1139",
        "FG": "96",
        "FGA": "303",
        "FG%": ".317",
        "3P": "",
        "3PA": "",
        "3P%": "",
        "2P": "96",
        "2PA": "303",
        "2P%": ".317",
        "eFG%": ".317",
        "FT": "95",
        "FTA": "123",
        "FT%": ".772",
        "ORB": "",
        "DRB": "",
        "TRB": "134",
        "AST": "104",
        "STL": "",
        "BLK": "",
        "TOV": "",
        "PF": "126",
        "PTS": "287"
    },
    {
        "Rk": "84",
        "Player": "Dolph Schayes*",
        "Pos": "PF",
        "Age": "26",
        "Tm": "SYR",
        "G": "72",
        "GS": "",
        "MP": "2526",
        "FG": "422",
        "FGA": "1103",
        "FG%": ".383",
        "3P": "",
        "3PA": "",
        "3P%": "",
        "2P": "422",
        "2PA": "1103",
        "2P%": ".383",
        "eFG%": ".383",
        "FT": "489",
        "FTA": "587",
        "FT%": ".833",
        "ORB": "",
        "DRB": "",
        "TRB": "887",
        "AST": "213",
        "STL": "",
        "BLK": "",
        "TOV": "",
        "PF": "247",
        "PTS": "1333"
    },
    {
        "Rk": "85",
        "Player": "Dick Schnittker",
        "Pos": "SF",
        "Age": "26",
        "Tm": "MNL",
        "G": "72",
        "GS": "",
        "MP": "1798",
        "FG": "226",
        "FGA": "583",
        "FG%": ".388",
        "3P": "",
        "3PA": "",
        "3P%": "",
        "2P": "226",
        "2PA": "583",
        "2P%": ".388",
        "eFG%": ".388",
        "FT": "298",
        "FTA": "362",
        "FT%": ".823",
        "ORB": "",
        "DRB": "",
        "TRB": "349",
        "AST": "114",
        "STL": "",
        "BLK": "",
        "TOV": "",
        "PF": "231",
        "PTS": "750"
    },
    {
        "Rk": "86",
        "Player": "Fred Scolari",
        "Pos": "PG",
        "Age": "32",
        "Tm": "BOS",
        "G": "59",
        "GS": "",
        "MP": "619",
        "FG": "76",
        "FGA": "249",
        "FG%": ".305",
        "3P": "",
        "3PA": "",
        "3P%": "",
        "2P": "76",
        "2PA": "249",
        "2P%": ".305",
        "eFG%": ".305",
        "FT": "39",
        "FTA": "49",
        "FT%": ".796",
        "ORB": "",
        "DRB": "",
        "TRB": "77",
        "AST": "93",
        "STL": "",
        "BLK": "",
        "TOV": "",
        "PF": "76",
        "PTS": "191"
    },
    {
        "Rk": "87",
        "Player": "Frank Selvy",
        "Pos": "G-F",
        "Age": "22",
        "Tm": "TOT",
        "G": "71",
        "GS": "",
        "MP": "2668",
        "FG": "452",
        "FGA": "1195",
        "FG%": ".378",
        "3P": "",
        "3PA": "",
        "3P%": "",
        "2P": "452",
        "2PA": "1195",
        "2P%": ".378",
        "eFG%": ".378",
        "FT": "444",
        "FTA": "610",
        "FT%": ".728",
        "ORB": "",
        "DRB": "",
        "TRB": "394",
        "AST": "245",
        "STL": "",
        "BLK": "",
        "TOV": "",
        "PF": "230",
        "PTS": "1348"
    },
    {
        "Rk": "88",
        "Player": "Paul Seymour",
        "Pos": "SG",
        "Age": "27",
        "Tm": "SYR",
        "G": "72",
        "GS": "",
        "MP": "2950",
        "FG": "375",
        "FGA": "1036",
        "FG%": ".362",
        "3P": "",
        "3PA": "",
        "3P%": "",
        "2P": "375",
        "2PA": "1036",
        "2P%": ".362",
        "eFG%": ".362",
        "FT": "300",
        "FTA": "370",
        "FT%": ".811",
        "ORB": "",
        "DRB": "",
        "TRB": "309",
        "AST": "483",
        "STL": "",
        "BLK": "",
        "TOV": "",
        "PF": "137",
        "PTS": "1050"
    },
    {
        "Rk": "89",
        "Player": "Chuck Share",
        "Pos": "C",
        "Age": "27",
        "Tm": "MLH",
        "G": "69",
        "GS": "",
        "MP": "1685",
        "FG": "235",
        "FGA": "577",
        "FG%": ".407",
        "3P": "",
        "3PA": "",
        "3P%": "",
        "2P": "235",
        "2PA": "577",
        "2P%": ".407",
        "eFG%": ".407",
        "FT": "351",
        "FTA": "492",
        "FT%": ".713",
        "ORB": "",
        "DRB": "",
        "TRB": "684",
        "AST": "84",
        "STL": "",
        "BLK": "",
        "TOV": "",
        "PF": "273",
        "PTS": "821"
    },
    {
        "Rk": "90",
        "Player": "Bill Sharman*",
        "Pos": "SG",
        "Age": "28",
        "Tm": "BOS",
        "G": "68",
        "GS": "",
        "MP": "2453",
        "FG": "453",
        "FGA": "1062",
        "FG%": ".427",
        "3P": "",
        "3PA": "",
        "3P%": "",
        "2P": "453",
        "2PA": "1062",
        "2P%": ".427",
        "eFG%": ".427",
        "FT": "347",
        "FTA": "387",
        "FT%": ".897",
        "ORB": "",
        "DRB": "",
        "TRB": "302",
        "AST": "280",
        "STL": "",
        "BLK": "",
        "TOV": "",
        "PF": "212",
        "PTS": "1253"
    },
    {
        "Rk": "91",
        "Player": "Gene Shue",
        "Pos": "PG",
        "Age": "23",
        "Tm": "TOT",
        "G": "62",
        "GS": "",
        "MP": "947",
        "FG": "100",
        "FGA": "289",
        "FG%": ".346",
        "3P": "",
        "3PA": "",
        "3P%": "",
        "2P": "100",
        "2PA": "289",
        "2P%": ".346",
        "eFG%": ".346",
        "FT": "59",
        "FTA": "78",
        "FT%": ".756",
        "ORB": "",
        "DRB": "",
        "TRB": "154",
        "AST": "89",
        "STL": "",
        "BLK": "",
        "TOV": "",
        "PF": "64",
        "PTS": "259"
    },
    {
        "Rk": "91",
        "Player": "Gene Shue",
        "Pos": "PG",
        "Age": "23",
        "Tm": "PHW",
        "G": "6",
        "GS": "",
        "MP": "65",
        "FG": "3",
        "FGA": "15",
        "FG%": ".200",
        "3P": "",
        "3PA": "",
        "3P%": "",
        "2P": "3",
        "2PA": "15",
        "2P%": ".200",
        "eFG%": ".200",
        "FT": "5",
        "FTA": "6",
        "FT%": ".833",
        "ORB": "",
        "DRB": "",
        "TRB": "10",
        "AST": "11",
        "STL": "",
        "BLK": "",
        "TOV": "",
        "PF": "4",
        "PTS": "11"
    },
    {
        "Rk": "91",
        "Player": "Gene Shue",
        "Pos": "PG",
        "Age": "23",
        "Tm": "NYK",
        "G": "56",
        "GS": "",
        "MP": "882",
        "FG": "97",
        "FGA": "274",
        "FG%": ".354",
        "3P": "",
        "3PA": "",
        "3P%": "",
        "2P": "97",
        "2PA": "274",
        "2P%": ".354",
        "eFG%": ".354",
        "FT": "54",
        "FTA": "72",
        "FT%": ".750",
        "ORB": "",
        "DRB": "",
        "TRB": "144",
        "AST": "78",
        "STL": "",
        "BLK": "",
        "TOV": "",
        "PF": "60",
        "PTS": "248"
    },
    {
        "Rk": "92",
        "Player": "Connie Simmons",
        "Pos": "C-F",
        "Age": "29",
        "Tm": "TOT",
        "G": "36",
        "GS": "",
        "MP": "862",
        "FG": "137",
        "FGA": "384",
        "FG%": ".357",
        "3P": "",
        "3PA": "",
        "3P%": "",
        "2P": "137",
        "2PA": "384",
        "2P%": ".357",
        "eFG%": ".357",
        "FT": "72",
        "FTA": "114",
        "FT%": ".632",
        "ORB": "",
        "DRB": "",
        "TRB": "220",
        "AST": "61",
        "STL": "",
        "BLK": "",
        "TOV": "",
        "PF": "109",
        "PTS": "346"
    },
    {
        "Rk": "93",
        "Player": "Whitey Skoog",
        "Pos": "SG",
        "Age": "28",
        "Tm": "MNL",
        "G": "72",
        "GS": "",
        "MP": "2365",
        "FG": "330",
        "FGA": "836",
        "FG%": ".395",
        "3P": "",
        "3PA": "",
        "3P%": "",
        "2P": "330",
        "2PA": "836",
        "2P%": ".395",
        "eFG%": ".395",
        "FT": "125",
        "FTA": "155",
        "FT%": ".806",
        "ORB": "",
        "DRB": "",
        "TRB": "303",
        "AST": "251",
        "STL": "",
        "BLK": "",
        "TOV": "",
        "PF": "265",
        "PTS": "785"
    },
    {
        "Rk": "94",
        "Player": "Odie Spears",
        "Pos": "SF",
        "Age": "29",
        "Tm": "ROC",
        "G": "71",
        "GS": "",
        "MP": "1888",
        "FG": "226",
        "FGA": "585",
        "FG%": ".386",
        "3P": "",
        "3PA": "",
        "3P%": "",
        "2P": "226",
        "2PA": "585",
        "2P%": ".386",
        "eFG%": ".386",
        "FT": "220",
        "FTA": "271",
        "FT%": ".812",
        "ORB": "",
        "DRB": "",
        "TRB": "299",
        "AST": "148",
        "STL": "",
        "BLK": "",
        "TOV": "",
        "PF": "252",
        "PTS": "672"
    },
    {
        "Rk": "95",
        "Player": "Art Spoelstra",
        "Pos": "C",
        "Age": "22",
        "Tm": "ROC",
        "G": "70",
        "GS": "",
        "MP": "1127",
        "FG": "159",
        "FGA": "399",
        "FG%": ".398",
        "3P": "",
        "3PA": "",
        "3P%": "",
        "2P": "159",
        "2PA": "399",
        "2P%": ".398",
        "eFG%": ".398",
        "FT": "108",
        "FTA": "156",
        "FT%": ".692",
        "ORB": "",
        "DRB": "",
        "TRB": "285",
        "AST": "58",
        "STL": "",
        "BLK": "",
        "TOV": "",
        "PF": "170",
        "PTS": "426"
    },
    {
        "Rk": "96",
        "Player": "Don Sunderlage",
        "Pos": "SG",
        "Age": "25",
        "Tm": "MNL",
        "G": "45",
        "GS": "",
        "MP": "404",
        "FG": "33",
        "FGA": "133",
        "FG%": ".248",
        "3P": "",
        "3PA": "",
        "3P%": "",
        "2P": "33",
        "2PA": "133",
        "2P%": ".248",
        "eFG%": ".248",
        "FT": "48",
        "FTA": "73",
        "FT%": ".658",
        "ORB": "",
        "DRB": "",
        "TRB": "56",
        "AST": "37",
        "STL": "",
        "BLK": "",
        "TOV": "",
        "PF": "57",
        "PTS": "114"
    },
    {
        "Rk": "97",
        "Player": "Jim Tucker",
        "Pos": "PF",
        "Age": "22",
        "Tm": "SYR",
        "G": "20",
        "GS": "",
        "MP": "287",
        "FG": "39",
        "FGA": "116",
        "FG%": ".336",
        "3P": "",
        "3PA": "",
        "3P%": "",
        "2P": "39",
        "2PA": "116",
        "2P%": ".336",
        "eFG%": ".336",
        "FT": "27",
        "FTA": "38",
        "FT%": ".711",
        "ORB": "",
        "DRB": "",
        "TRB": "97",
        "AST": "12",
        "STL": "",
        "BLK": "",
        "TOV": "",
        "PF": "50",
        "PTS": "105"
    },
    {
        "Rk": "98",
        "Player": "Jack Turner",
        "Pos": "SF",
        "Age": "24",
        "Tm": "NYK",
        "G": "65",
        "GS": "",
        "MP": "922",
        "FG": "111",
        "FGA": "308",
        "FG%": ".360",
        "3P": "",
        "3PA": "",
        "3P%": "",
        "2P": "111",
        "2PA": "308",
        "2P%": ".360",
        "eFG%": ".360",
        "FT": "60",
        "FTA": "76",
        "FT%": ".789",
        "ORB": "",
        "DRB": "",
        "TRB": "154",
        "AST": "77",
        "STL": "",
        "BLK": "",
        "TOV": "",
        "PF": "76",
        "PTS": "282"
    },
    {
        "Rk": "99",
        "Player": "Paul Walther",
        "Pos": "SG",
        "Age": "27",
        "Tm": "FTW",
        "G": "68",
        "GS": "",
        "MP": "820",
        "FG": "56",
        "FGA": "161",
        "FG%": ".348",
        "3P": "",
        "3PA": "",
        "3P%": "",
        "2P": "56",
        "2PA": "161",
        "2P%": ".348",
        "eFG%": ".348",
        "FT": "54",
        "FTA": "88",
        "FT%": ".614",
        "ORB": "",
        "DRB": "",
        "TRB": "155",
        "AST": "131",
        "STL": "",
        "BLK": "",
        "TOV": "",
        "PF": "115",
        "PTS": "166"
    },
    {
        "Rk": "100",
        "Player": "Bobby Wanzer*",
        "Pos": "SG",
        "Age": "33",
        "Tm": "ROC",
        "G": "72",
        "GS": "",
        "MP": "2376",
        "FG": "324",
        "FGA": "820",
        "FG%": ".395",
        "3P": "",
        "3PA": "",
        "3P%": "",
        "2P": "324",
        "2PA": "820",
        "2P%": ".395",
        "eFG%": ".395",
        "FT": "294",
        "FTA": "374",
        "FT%": ".786",
        "ORB": "",
        "DRB": "",
        "TRB": "374",
        "AST": "247",
        "STL": "",
        "BLK": "",
        "TOV": "",
        "PF": "163",
        "PTS": "942"
    },
    {
        "Rk": "Rk",
        "Player": "Player",
        "Pos": "Pos",
        "Age": "Age",
        "Tm": "Tm",
        "G": "G",
        "GS": "GS",
        "MP": "MP",
        "FG": "FG",
        "FGA": "FGA",
        "FG%": "FG%",
        "3P": "3P",
        "3PA": "3PA",
        "3P%": "3P%",
        "2P": "2P",
        "2PA": "2PA",
        "2P%": "2P%",
        "eFG%": "eFG%",
        "FT": "FT",
        "FTA": "FTA",
        "FT%": "FT%",
        "ORB": "ORB",
        "DRB": "DRB",
        "TRB": "TRB",
        "AST": "AST",
        "STL": "STL",
        "BLK": "BLK",
        "TOV": "TOV",
        "PF": "PF",
        "PTS": "PTS"
    },
    {
        "Rk": "101",
        "Player": "Bobby Watson",
        "Pos": "G",
        "Age": "24",
        "Tm": "TOT",
        "G": "63",
        "GS": "",
        "MP": "702",
        "FG": "72",
        "FGA": "223",
        "FG%": ".323",
        "3P": "",
        "3PA": "",
        "3P%": "",
        "2P": "72",
        "2PA": "223",
        "2P%": ".323",
        "eFG%": ".323",
        "FT": "31",
        "FTA": "45",
        "FT%": ".689",
        "ORB": "",
        "DRB": "",
        "TRB": "87",
        "AST": "79",
        "STL": "",
        "BLK": "",
        "TOV": "",
        "PF": "67",
        "PTS": "175"
    },
    {
        "Rk": "102",
        "Player": "Skippy Whitaker",
        "Pos": "PG",
        "Age": "24",
        "Tm": "BOS",
        "G": "3",
        "GS": "",
        "MP": "15",
        "FG": "1",
        "FGA": "6",
        "FG%": ".167",
        "3P": "",
        "3PA": "",
        "3P%": "",
        "2P": "1",
        "2PA": "6",
        "2P%": ".167",
        "eFG%": ".167",
        "FT": "0",
        "FTA": "0",
        "FT%": "",
        "ORB": "",
        "DRB": "",
        "TRB": "1",
        "AST": "1",
        "STL": "",
        "BLK": "",
        "TOV": "",
        "PF": "4",
        "PTS": "2"
    },
    {
        "Rk": "103",
        "Player": "George Yardley*",
        "Pos": "SF",
        "Age": "26",
        "Tm": "FTW",
        "G": "60",
        "GS": "",
        "MP": "2150",
        "FG": "363",
        "FGA": "869",
        "FG%": ".418",
        "3P": "",
        "3PA": "",
        "3P%": "",
        "2P": "363",
        "2PA": "869",
        "2P%": ".418",
        "eFG%": ".418",
        "FT": "310",
        "FTA": "416",
        "FT%": ".745",
        "ORB": "",
        "DRB": "",
        "TRB": "594",
        "AST": "126",
        "STL": "",
        "BLK": "",
        "TOV": "",
        "PF": "205",
        "PTS": "1036"
    },
    {
        "Rk": "104",
        "Player": "Max Zaslofsky",
        "Pos": "SG",
        "Age": "29",
        "Tm": "FTW",
        "G": "70",
        "GS": "",
        "MP": "1862",
        "FG": "269",
        "FGA": "821",
        "FG%": ".328",
        "3P": "",
        "3PA": "",
        "3P%": "",
        "2P": "269",
        "2PA": "821",
        "2P%": ".328",
        "eFG%": ".328",
        "FT": "247",
        "FTA": "352",
        "FT%": ".702",
        "ORB": "",
        "DRB": "",
        "TRB": "191",
        "AST": "203",
        "STL": "",
        "BLK": "",
        "TOV": "",
        "PF": "130",
        "PTS": "785"
    },
    {
        "Rk": "105",
        "Player": "Zeke Zawoluk",
        "Pos": "PF",
        "Age": "24",
        "Tm": "PHW",
        "G": "67",
        "GS": "",
        "MP": "1117",
        "FG": "138",
        "FGA": "375",
        "FG%": ".368",
        "3P": "",
        "3PA": "",
        "3P%": "",
        "2P": "138",
        "2PA": "375",
        "2P%": ".368",
        "eFG%": ".368",
        "FT": "155",
        "FTA": "199",
        "FT%": ".779",
        "ORB": "",
        "DRB": "",
        "TRB": "256",
        "AST": "87",
        "STL": "",
        "BLK": "",
        "TOV": "",
        "PF": "147",
        "PTS": "431"
    }
]