[
    {
        "Player": "Alaa Abdelnaby",
        "From": "1991",
        "To": "1995",
        "Pos": "F-C",
        "Ht": "6-10",
        "Wt": "240",
        "Birth Date": "June 24 1968",
        "College": "Duke University"
    },
    {
        "Player": "Zaid Abdul-Aziz",
        "From": "1969",
        "To": "1978",
        "Pos": "C-F",
        "Ht": "6-9",
        "Wt": "235",
        "Birth Date": "April 7 1946",
        "College": "Iowa State University"
    },
    {
        "Player": "Kareem Abdul-Jabbar*",
        "From": "1970",
        "To": "1989",
        "Pos": "C",
        "Ht": "7-2",
        "Wt": "225",
        "Birth Date": "April 16 1947",
        "College": "University of California Los Angeles"
    },
    {
        "Player": "Mahdi Abdul-Rahman",
        "From": "1965",
        "To": "1974",
        "Pos": "G",
        "Ht": "6-2",
        "Wt": "185",
        "Birth Date": "April 15 1942",
        "College": "University of California Los Angeles"
    },
    {
        "Player": "Mahmoud Abdul-Rauf",
        "From": "1991",
        "To": "2001",
        "Pos": "G",
        "Ht": "6-1",
        "Wt": "162",
        "Birth Date": "March 9 1969",
        "College": "Louisiana State University"
    },
    {
        "Player": "Tariq Abdul-Wahad",
        "From": "1998",
        "To": "2003",
        "Pos": "F",
        "Ht": "6-6",
        "Wt": "223",
        "Birth Date": "November 3 1974",
        "College": "San Jose State University"
    },
    {
        "Player": "Shareef Abdur-Rahim",
        "From": "1997",
        "To": "2008",
        "Pos": "F",
        "Ht": "6-9",
        "Wt": "225",
        "Birth Date": "December 11 1976",
        "College": "University of California"
    },
    {
        "Player": "Tom Abernethy",
        "From": "1977",
        "To": "1981",
        "Pos": "F",
        "Ht": "6-7",
        "Wt": "220",
        "Birth Date": "May 6 1954",
        "College": "Indiana University"
    },
    {
        "Player": "Forest Able",
        "From": "1957",
        "To": "1957",
        "Pos": "G",
        "Ht": "6-3",
        "Wt": "180",
        "Birth Date": "July 27 1932",
        "College": "Western Kentucky University"
    },
    {
        "Player": "John Abramovic",
        "From": "1947",
        "To": "1948",
        "Pos": "F",
        "Ht": "6-3",
        "Wt": "195",
        "Birth Date": "February 9 1919",
        "College": "Salem International University"
    },
    {
        "Player": "Alex Acker",
        "From": "2006",
        "To": "2009",
        "Pos": "G",
        "Ht": "6-5",
        "Wt": "185",
        "Birth Date": "January 21 1983",
        "College": "Pepperdine University"
    },
    {
        "Player": "Don Ackerman",
        "From": "1954",
        "To": "1954",
        "Pos": "G",
        "Ht": "6-0",
        "Wt": "183",
        "Birth Date": "September 4 1930",
        "College": "Long Island University"
    },
    {
        "Player": "Mark Acres",
        "From": "1988",
        "To": "1993",
        "Pos": "F-C",
        "Ht": "6-11",
        "Wt": "220",
        "Birth Date": "November 15 1962",
        "College": "Oral Roberts University"
    },
    {
        "Player": "Bud Acton",
        "From": "1968",
        "To": "1968",
        "Pos": "F",
        "Ht": "6-6",
        "Wt": "210",
        "Birth Date": "January 11 1942",
        "College": "Hillsdale College"
    },
    {
        "Player": "Quincy Acy",
        "From": "2013",
        "To": "2015",
        "Pos": "F",
        "Ht": "6-7",
        "Wt": "233",
        "Birth Date": "October 6 1990",
        "College": "Baylor University"
    },
    {
        "Player": "Alvan Adams",
        "From": "1976",
        "To": "1988",
        "Pos": "C-F",
        "Ht": "6-9",
        "Wt": "210",
        "Birth Date": "July 19 1954",
        "College": "University of Oklahoma"
    },
    {
        "Player": "Don Adams",
        "From": "1971",
        "To": "1977",
        "Pos": "F",
        "Ht": "6-6",
        "Wt": "210",
        "Birth Date": "November 27 1947",
        "College": "Northwestern University"
    },
    {
        "Player": "George Adams",
        "From": "1973",
        "To": "1975",
        "Pos": "F-G",
        "Ht": "6-5",
        "Wt": "210",
        "Birth Date": "May 15 1949",
        "College": "Gardner-Webb University"
    },
    {
        "Player": "Hassan Adams",
        "From": "2007",
        "To": "2009",
        "Pos": "G",
        "Ht": "6-4",
        "Wt": "220",
        "Birth Date": "June 20 1984",
        "College": "University of Arizona"
    },
    {
        "Player": "Jordan Adams",
        "From": "2015",
        "To": "2015",
        "Pos": "G",
        "Ht": "6-5",
        "Wt": "220",
        "Birth Date": "July 8 1994",
        "College": "University of California Los Angeles"
    },
    {
        "Player": "Michael Adams",
        "From": "1986",
        "To": "1996",
        "Pos": "G",
        "Ht": "5-10",
        "Wt": "162",
        "Birth Date": "January 19 1963",
        "College": "Boston College"
    },
    {
        "Player": "Steven Adams",
        "From": "2014",
        "To": "2015",
        "Pos": "C",
        "Ht": "7-0",
        "Wt": "250",
        "Birth Date": "July 28 1993",
        "College": "University of Pittsburgh"
    },
    {
        "Player": "Rafael Addison",
        "From": "1987",
        "To": "1997",
        "Pos": "F-G",
        "Ht": "6-7",
        "Wt": "215",
        "Birth Date": "July 22 1964",
        "College": "Syracuse University"
    },
    {
        "Player": "Rick Adelman",
        "From": "1969",
        "To": "1975",
        "Pos": "G",
        "Ht": "6-1",
        "Wt": "175",
        "Birth Date": "June 16 1946",
        "College": "Loyola Marymount University"
    },
    {
        "Player": "Jeff Adrien",
        "From": "2011",
        "To": "2015",
        "Pos": "F",
        "Ht": "6-7",
        "Wt": "243",
        "Birth Date": "February 10 1986",
        "College": "University of Connecticut"
    },
    {
        "Player": "Arron Afflalo",
        "From": "2008",
        "To": "2015",
        "Pos": "G",
        "Ht": "6-5",
        "Wt": "215",
        "Birth Date": "October 15 1985",
        "College": "University of California Los Angeles"
    },
    {
        "Player": "Maurice Ager",
        "From": "2007",
        "To": "2011",
        "Pos": "G",
        "Ht": "6-5",
        "Wt": "202",
        "Birth Date": "February 9 1984",
        "College": "Michigan State University"
    },
    {
        "Player": "Mark Aguirre",
        "From": "1982",
        "To": "1994",
        "Pos": "F-G",
        "Ht": "6-6",
        "Wt": "232",
        "Birth Date": "December 10 1959",
        "College": "DePaul University"
    },
    {
        "Player": "Blake Ahearn",
        "From": "2008",
        "To": "2012",
        "Pos": "G",
        "Ht": "6-2",
        "Wt": "190",
        "Birth Date": "May 27 1984",
        "College": "Missouri State University"
    },
    {
        "Player": "Danny Ainge",
        "From": "1982",
        "To": "1995",
        "Pos": "G",
        "Ht": "6-4",
        "Wt": "175",
        "Birth Date": "March 17 1959",
        "College": "Brigham Young University"
    },
    {
        "Player": "Matthew Aitch",
        "From": "1968",
        "To": "1968",
        "Pos": "F",
        "Ht": "6-7",
        "Wt": "230",
        "Birth Date": "September 21 1944",
        "College": "Michigan State University"
    },
    {
        "Player": "Alexis Ajinca",
        "From": "2009",
        "To": "2015",
        "Pos": "C",
        "Ht": "7-0",
        "Wt": "220",
        "Birth Date": "May 6 1988",
        "College": ""
    },
    {
        "Player": "Henry Akin",
        "From": "1967",
        "To": "1969",
        "Pos": "C-F",
        "Ht": "6-10",
        "Wt": "225",
        "Birth Date": "July 31 1944",
        "College": "Morehead State University"
    },
    {
        "Player": "Josh Akognon",
        "From": "2013",
        "To": "2013",
        "Pos": "G",
        "Ht": "5-11",
        "Wt": "185",
        "Birth Date": "February 10 1986",
        "College": "California State University Fullerton"
    },
    {
        "Player": "Solomon Alabi",
        "From": "2011",
        "To": "2012",
        "Pos": "C",
        "Ht": "7-1",
        "Wt": "251",
        "Birth Date": "March 21 1988",
        "College": "Florida State University"
    },
    {
        "Player": "Mark Alarie",
        "From": "1987",
        "To": "1991",
        "Pos": "F",
        "Ht": "6-8",
        "Wt": "217",
        "Birth Date": "December 11 1963",
        "College": "Duke University"
    },
    {
        "Player": "Gary Alcorn",
        "From": "1960",
        "To": "1961",
        "Pos": "C",
        "Ht": "6-9",
        "Wt": "225",
        "Birth Date": "October 8 1936",
        "College": "California State University Fresno"
    },
    {
        "Player": "Cole Aldrich",
        "From": "2011",
        "To": "2015",
        "Pos": "C",
        "Ht": "6-11",
        "Wt": "245",
        "Birth Date": "October 31 1988",
        "College": "University of Kansas"
    },
    {
        "Player": "LaMarcus Aldridge",
        "From": "2007",
        "To": "2015",
        "Pos": "F",
        "Ht": "6-11",
        "Wt": "240",
        "Birth Date": "July 19 1985",
        "College": "University of Texas at Austin"
    },
    {
        "Player": "Chuck Aleksinas",
        "From": "1985",
        "To": "1985",
        "Pos": "C",
        "Ht": "6-11",
        "Wt": "260",
        "Birth Date": "February 26 1959",
        "College": "University of Connecticut"
    },
    {
        "Player": "Cory Alexander",
        "From": "1996",
        "To": "2005",
        "Pos": "G",
        "Ht": "6-1",
        "Wt": "185",
        "Birth Date": "June 22 1973",
        "College": "University of Virginia"
    },
    {
        "Player": "Courtney Alexander",
        "From": "2001",
        "To": "2003",
        "Pos": "G",
        "Ht": "6-5",
        "Wt": "205",
        "Birth Date": "April 27 1977",
        "College": "California State University Fresno"
    },
    {
        "Player": "Gary Alexander",
        "From": "1994",
        "To": "1994",
        "Pos": "F",
        "Ht": "6-7",
        "Wt": "240",
        "Birth Date": "November 1 1969",
        "College": "University of South Florida"
    },
    {
        "Player": "Joe Alexander",
        "From": "2009",
        "To": "2010",
        "Pos": "F",
        "Ht": "6-8",
        "Wt": "230",
        "Birth Date": "December 26 1986",
        "College": "West Virginia University"
    },
    {
        "Player": "Victor Alexander",
        "From": "1992",
        "To": "2002",
        "Pos": "C-F",
        "Ht": "6-9",
        "Wt": "265",
        "Birth Date": "August 31 1969",
        "College": "Iowa State University"
    },
    {
        "Player": "Steve Alford",
        "From": "1988",
        "To": "1991",
        "Pos": "G",
        "Ht": "6-2",
        "Wt": "183",
        "Birth Date": "November 23 1964",
        "College": "Indiana University"
    },
    {
        "Player": "Bill Allen",
        "From": "1968",
        "To": "1968",
        "Pos": "C-F",
        "Ht": "6-8",
        "Wt": "205",
        "Birth Date": "",
        "College": "New Mexico State University"
    },
    {
        "Player": "Bob Allen",
        "From": "1969",
        "To": "1969",
        "Pos": "F",
        "Ht": "6-9",
        "Wt": "205",
        "Birth Date": "July 17 1946",
        "College": "Marshall University"
    },
    {
        "Player": "Jerome Allen",
        "From": "1996",
        "To": "1997",
        "Pos": "G",
        "Ht": "6-4",
        "Wt": "184",
        "Birth Date": "January 28 1973",
        "College": "University of Pennsylvania"
    },
    {
        "Player": "Lavoy Allen",
        "From": "2012",
        "To": "2015",
        "Pos": "F",
        "Ht": "6-9",
        "Wt": "225",
        "Birth Date": "February 4 1989",
        "College": "Temple University"
    },
    {
        "Player": "Lucius Allen",
        "From": "1970",
        "To": "1979",
        "Pos": "G",
        "Ht": "6-2",
        "Wt": "175",
        "Birth Date": "September 26 1947",
        "College": "University of California Los Angeles"
    },
    {
        "Player": "Malik Allen",
        "From": "2002",
        "To": "2011",
        "Pos": "F",
        "Ht": "6-10",
        "Wt": "255",
        "Birth Date": "June 27 1978",
        "College": "Villanova University"
    },
    {
        "Player": "Randy Allen",
        "From": "1989",
        "To": "1990",
        "Pos": "F",
        "Ht": "6-8",
        "Wt": "220",
        "Birth Date": "January 26 1965",
        "College": "Florida State University"
    },
    {
        "Player": "Ray Allen",
        "From": "1997",
        "To": "2014",
        "Pos": "G",
        "Ht": "6-5",
        "Wt": "205",
        "Birth Date": "July 20 1975",
        "College": "University of Connecticut"
    },
    {
        "Player": "Tony Allen",
        "From": "2005",
        "To": "2015",
        "Pos": "G",
        "Ht": "6-4",
        "Wt": "213",
        "Birth Date": "January 11 1982",
        "College": "Oklahoma State University"
    },
    {
        "Player": "Willie Allen",
        "From": "1972",
        "To": "1972",
        "Pos": "F",
        "Ht": "6-6",
        "Wt": "230",
        "Birth Date": "February 8 1949",
        "College": "University of Miami"
    },
    {
        "Player": "Odis Allison",
        "From": "1972",
        "To": "1972",
        "Pos": "F",
        "Ht": "6-6",
        "Wt": "195",
        "Birth Date": "October 2 1949",
        "College": "University of Nevada Las Vegas"
    },
    {
        "Player": "Lance Allred",
        "From": "2008",
        "To": "2008",
        "Pos": "C",
        "Ht": "6-11",
        "Wt": "250",
        "Birth Date": "February 2 1981",
        "College": "Weber State University"
    },
    {
        "Player": "Darrell Allums",
        "From": "1981",
        "To": "1981",
        "Pos": "F",
        "Ht": "6-9",
        "Wt": "220",
        "Birth Date": "September 12 1958",
        "College": "University of California Los Angeles"
    },
    {
        "Player": "Morris Almond",
        "From": "2008",
        "To": "2012",
        "Pos": "G",
        "Ht": "6-6",
        "Wt": "225",
        "Birth Date": "February 2 1985",
        "College": "Rice University"
    },
    {
        "Player": "Derrick Alston",
        "From": "1995",
        "To": "1997",
        "Pos": "F",
        "Ht": "6-11",
        "Wt": "225",
        "Birth Date": "August 20 1972",
        "College": "Duquesne University"
    },
    {
        "Player": "Rafer Alston",
        "From": "2000",
        "To": "2010",
        "Pos": "G",
        "Ht": "6-2",
        "Wt": "171",
        "Birth Date": "July 24 1976",
        "College": "California State University Fresno"
    },
    {
        "Player": "Peter Aluma",
        "From": "1999",
        "To": "1999",
        "Pos": "C",
        "Ht": "6-10",
        "Wt": "260",
        "Birth Date": "April 23 1973",
        "College": "Liberty University"
    },
    {
        "Player": "John Amaechi",
        "From": "1996",
        "To": "2003",
        "Pos": "C-F",
        "Ht": "6-10",
        "Wt": "270",
        "Birth Date": "November 26 1970",
        "College": "Pennsylvania State University"
    },
    {
        "Player": "Ashraf Amaya",
        "From": "1996",
        "To": "1997",
        "Pos": "F",
        "Ht": "6-8",
        "Wt": "230",
        "Birth Date": "November 23 1971",
        "College": "Southern Illinois University"
    },
    {
        "Player": "Al-Farouq Aminu",
        "From": "2011",
        "To": "2015",
        "Pos": "F",
        "Ht": "6-9",
        "Wt": "215",
        "Birth Date": "September 21 1990",
        "College": "Wake Forest University"
    },
    {
        "Player": "Louis Amundson",
        "From": "2007",
        "To": "2015",
        "Pos": "F",
        "Ht": "6-9",
        "Wt": "225",
        "Birth Date": "December 7 1982",
        "College": "University of Nevada Las Vegas"
    },
    {
        "Player": "Bob Anderegg",
        "From": "1960",
        "To": "1960",
        "Pos": "F-G",
        "Ht": "6-3",
        "Wt": "200",
        "Birth Date": "August 24 1937",
        "College": "Michigan State University"
    },
    {
        "Player": "Chris Andersen",
        "From": "2002",
        "To": "2015",
        "Pos": "F",
        "Ht": "6-10",
        "Wt": "230",
        "Birth Date": "July 7 1978",
        "College": "Blinn College"
    },
    {
        "Player": "David Andersen",
        "From": "2010",
        "To": "2011",
        "Pos": "C",
        "Ht": "6-11",
        "Wt": "245",
        "Birth Date": "June 23 1980",
        "College": ""
    },
    {
        "Player": "Alan Anderson",
        "From": "2006",
        "To": "2015",
        "Pos": "G-F",
        "Ht": "6-6",
        "Wt": "220",
        "Birth Date": "October 16 1982",
        "College": "Michigan State University"
    },
    {
        "Player": "Andrew Anderson",
        "From": "1968",
        "To": "1970",
        "Pos": "G",
        "Ht": "6-2",
        "Wt": "184",
        "Birth Date": "July 6 1945",
        "College": "Canisius College"
    },
    {
        "Player": "Antonio Anderson",
        "From": "2010",
        "To": "2010",
        "Pos": "G",
        "Ht": "6-6",
        "Wt": "215",
        "Birth Date": "June 5 1985",
        "College": "University of Memphis"
    },
    {
        "Player": "Cliff Anderson",
        "From": "1968",
        "To": "1971",
        "Pos": "G-F",
        "Ht": "6-2",
        "Wt": "200",
        "Birth Date": "September 7 1944",
        "College": "Saint Joseph's University"
    },
    {
        "Player": "Dan Anderson",
        "From": "1968",
        "To": "1969",
        "Pos": "C",
        "Ht": "6-10",
        "Wt": "230",
        "Birth Date": "February 15 1943",
        "College": "Augsburg College"
    },
    {
        "Player": "Dan Anderson",
        "From": "1975",
        "To": "1976",
        "Pos": "G",
        "Ht": "6-2",
        "Wt": "185",
        "Birth Date": "January 1 1951",
        "College": "University of Southern California"
    },
    {
        "Player": "Derek Anderson",
        "From": "1998",
        "To": "2008",
        "Pos": "G",
        "Ht": "6-5",
        "Wt": "194",
        "Birth Date": "July 18 1974",
        "College": "University of Kentucky"
    },
    {
        "Player": "Dwight Anderson",
        "From": "1983",
        "To": "1983",
        "Pos": "G",
        "Ht": "6-3",
        "Wt": "185",
        "Birth Date": "December 28 1960",
        "College": "University of Southern California"
    },
    {
        "Player": "Eric Anderson",
        "From": "1993",
        "To": "1994",
        "Pos": "F",
        "Ht": "6-9",
        "Wt": "220",
        "Birth Date": "May 26 1970",
        "College": "Indiana University"
    },
    {
        "Player": "Greg Anderson",
        "From": "1988",
        "To": "1998",
        "Pos": "F-C",
        "Ht": "6-10",
        "Wt": "230",
        "Birth Date": "June 22 1964",
        "College": "University of Houston"
    },
    {
        "Player": "J.J. Anderson",
        "From": "1983",
        "To": "1985",
        "Pos": "F",
        "Ht": "6-8",
        "Wt": "195",
        "Birth Date": "September 23 1960",
        "College": "Bradley University"
    },
    {
        "Player": "James Anderson",
        "From": "2011",
        "To": "2014",
        "Pos": "G",
        "Ht": "6-6",
        "Wt": "215",
        "Birth Date": "March 25 1989",
        "College": "Oklahoma State University"
    },
    {
        "Player": "Jerome Anderson",
        "From": "1976",
        "To": "1977",
        "Pos": "G",
        "Ht": "6-5",
        "Wt": "195",
        "Birth Date": "October 9 1953",
        "College": "West Virginia University"
    },
    {
        "Player": "Kenny Anderson",
        "From": "1992",
        "To": "2005",
        "Pos": "G",
        "Ht": "6-0",
        "Wt": "168",
        "Birth Date": "October 9 1970",
        "College": "Georgia Institute of Technology"
    },
    {
        "Player": "Kim Anderson",
        "From": "1979",
        "To": "1979",
        "Pos": "F",
        "Ht": "6-7",
        "Wt": "200",
        "Birth Date": "May 12 1955",
        "College": "University of Missouri"
    },
    {
        "Player": "Kyle Anderson",
        "From": "2015",
        "To": "2015",
        "Pos": "G-F",
        "Ht": "6-9",
        "Wt": "230",
        "Birth Date": "September 20 1993",
        "College": "University of California Los Angeles"
    },
    {
        "Player": "Michael Anderson",
        "From": "1989",
        "To": "1989",
        "Pos": "G",
        "Ht": "5-11",
        "Wt": "184",
        "Birth Date": "March 23 1966",
        "College": "Drexel University"
    },
    {
        "Player": "Nick Anderson",
        "From": "1990",
        "To": "2002",
        "Pos": "F-G",
        "Ht": "6-6",
        "Wt": "205",
        "Birth Date": "January 20 1968",
        "College": "University of Illinois at Urbana-Champaign"
    },
    {
        "Player": "Richard Anderson",
        "From": "1983",
        "To": "1990",
        "Pos": "F-C",
        "Ht": "6-10",
        "Wt": "240",
        "Birth Date": "November 19 1960",
        "College": "University of California Santa Barbara"
    },
    {
        "Player": "Ron Anderson",
        "From": "1985",
        "To": "1994",
        "Pos": "F-G",
        "Ht": "6-7",
        "Wt": "215",
        "Birth Date": "October 15 1958",
        "College": "California State University Fresno"
    },
    {
        "Player": "Ryan Anderson",
        "From": "2009",
        "To": "2015",
        "Pos": "F",
        "Ht": "6-10",
        "Wt": "240",
        "Birth Date": "May 6 1988",
        "College": "University of California"
    },
    {
        "Player": "Shandon Anderson",
        "From": "1997",
        "To": "2006",
        "Pos": "F-G",
        "Ht": "6-6",
        "Wt": "208",
        "Birth Date": "December 31 1973",
        "College": "University of Georgia"
    },
    {
        "Player": "Willie Anderson",
        "From": "1989",
        "To": "1997",
        "Pos": "G-F",
        "Ht": "6-7",
        "Wt": "190",
        "Birth Date": "January 8 1967",
        "College": "University of Georgia"
    },
    {
        "Player": "Wally Anderzunas",
        "From": "1970",
        "To": "1970",
        "Pos": "C-F",
        "Ht": "6-7",
        "Wt": "220",
        "Birth Date": "January 11 1946",
        "College": "Creighton University"
    },
    {
        "Player": "Martynas Andriuskevicius",
        "From": "2006",
        "To": "2006",
        "Pos": "C",
        "Ht": "7-2",
        "Wt": "240",
        "Birth Date": "March 12 1986",
        "College": ""
    },
    {
        "Player": "Don Anielak",
        "From": "1955",
        "To": "1955",
        "Pos": "F",
        "Ht": "6-7",
        "Wt": "190",
        "Birth Date": "November 1 1930",
        "College": "Missouri State University"
    },
    {
        "Player": "Michael Ansley",
        "From": "1990",
        "To": "1992",
        "Pos": "F",
        "Ht": "6-7",
        "Wt": "225",
        "Birth Date": "February 8 1967",
        "College": "University of Alabama"
    },
    {
        "Player": "Chris Anstey",
        "From": "1998",
        "To": "2000",
        "Pos": "C",
        "Ht": "7-0",
        "Wt": "249",
        "Birth Date": "January 1 1975",
        "College": ""
    },
    {
        "Player": "Giannis Antetokounmpo",
        "From": "2014",
        "To": "2015",
        "Pos": "G-F",
        "Ht": "6-11",
        "Wt": "217",
        "Birth Date": "December 6 1994",
        "College": ""
    },
    {
        "Player": "Carmelo Anthony",
        "From": "2004",
        "To": "2015",
        "Pos": "F",
        "Ht": "6-8",
        "Wt": "230",
        "Birth Date": "May 29 1984",
        "College": "Syracuse University"
    },
    {
        "Player": "Greg Anthony",
        "From": "1992",
        "To": "2002",
        "Pos": "G",
        "Ht": "6-0",
        "Wt": "176",
        "Birth Date": "November 15 1967",
        "College": "University of Nevada Las Vegas"
    },
    {
        "Player": "Joel Anthony",
        "From": "2008",
        "To": "2015",
        "Pos": "C",
        "Ht": "6-9",
        "Wt": "245",
        "Birth Date": "August 9 1982",
        "College": "University of Nevada Las Vegas"
    },
    {
        "Player": "Pero Antic",
        "From": "2014",
        "To": "2015",
        "Pos": "F",
        "Ht": "6-11",
        "Wt": "260",
        "Birth Date": "July 29 1982",
        "College": ""
    },
    {
        "Player": "Rafael Araujo",
        "From": "2005",
        "To": "2007",
        "Pos": "C",
        "Ht": "6-11",
        "Wt": "280",
        "Birth Date": "August 12 1980",
        "College": "Brigham Young University"
    },
    {
        "Player": "Stacey Arceneaux",
        "From": "1962",
        "To": "1962",
        "Pos": "F",
        "Ht": "6-4",
        "Wt": "210",
        "Birth Date": "February 17 1936",
        "College": "Iowa State University"
    },
    {
        "Player": "Robert Archibald",
        "From": "2003",
        "To": "2004",
        "Pos": "F",
        "Ht": "6-11",
        "Wt": "250",
        "Birth Date": "March 29 1980",
        "College": "University of Illinois at Urbana-Champaign"
    },
    {
        "Player": "Tiny Archibald*",
        "From": "1971",
        "To": "1984",
        "Pos": "G",
        "Ht": "6-1",
        "Wt": "150",
        "Birth Date": "September 2 1948",
        "College": "University of Texas at El Paso"
    },
    {
        "Player": "Jim Ard",
        "From": "1971",
        "To": "1978",
        "Pos": "F-C",
        "Ht": "6-8",
        "Wt": "215",
        "Birth Date": "September 19 1948",
        "College": "University of Cincinnati"
    },
    {
        "Player": "Gilbert Arenas",
        "From": "2002",
        "To": "2012",
        "Pos": "G",
        "Ht": "6-3",
        "Wt": "191",
        "Birth Date": "January 6 1982",
        "College": "University of Arizona"
    },
    {
        "Player": "Trevor Ariza",
        "From": "2005",
        "To": "2015",
        "Pos": "F",
        "Ht": "6-8",
        "Wt": "200",
        "Birth Date": "June 30 1985",
        "College": "University of California Los Angeles"
    },
    {
        "Player": "Paul Arizin*",
        "From": "1951",
        "To": "1962",
        "Pos": "F-G",
        "Ht": "6-4",
        "Wt": "190",
        "Birth Date": "April 9 1928",
        "College": "Villanova University"
    },
    {
        "Player": "Joe Arlauckas",
        "From": "1988",
        "To": "1988",
        "Pos": "F",
        "Ht": "6-9",
        "Wt": "230",
        "Birth Date": "July 20 1965",
        "College": "Niagara University"
    },
    {
        "Player": "B.J. Armstrong",
        "From": "1990",
        "To": "2000",
        "Pos": "G",
        "Ht": "6-2",
        "Wt": "175",
        "Birth Date": "September 9 1967",
        "College": "University of Iowa"
    },
    {
        "Player": "Bob Armstrong",
        "From": "1957",
        "To": "1957",
        "Pos": "C-F",
        "Ht": "6-8",
        "Wt": "220",
        "Birth Date": "June 17 1933",
        "College": "Michigan State University"
    },
    {
        "Player": "Brandon Armstrong",
        "From": "2002",
        "To": "2004",
        "Pos": "G",
        "Ht": "6-5",
        "Wt": "188",
        "Birth Date": "June 16 1980",
        "College": "Pepperdine University"
    },
    {
        "Player": "Curly Armstrong",
        "From": "1949",
        "To": "1951",
        "Pos": "G-F",
        "Ht": "5-11",
        "Wt": "170",
        "Birth Date": "November 1 1918",
        "College": "Indiana University"
    },
    {
        "Player": "Darrell Armstrong",
        "From": "1995",
        "To": "2008",
        "Pos": "G",
        "Ht": "6-0",
        "Wt": "170",
        "Birth Date": "June 22 1968",
        "College": "Fayetteville State University"
    },
    {
        "Player": "Hilton Armstrong",
        "From": "2007",
        "To": "2014",
        "Pos": "F-C",
        "Ht": "6-11",
        "Wt": "235",
        "Birth Date": "November 11 1984",
        "College": "University of Connecticut"
    },
    {
        "Player": "Tate Armstrong",
        "From": "1978",
        "To": "1979",
        "Pos": "G",
        "Ht": "6-3",
        "Wt": "175",
        "Birth Date": "October 5 1955",
        "College": "Duke University"
    },
    {
        "Player": "Jesse Arnelle",
        "From": "1956",
        "To": "1956",
        "Pos": "F",
        "Ht": "6-5",
        "Wt": "220",
        "Birth Date": "December 30 1933",
        "College": "Pennsylvania State University"
    },
    {
        "Player": "Jay Arnette",
        "From": "1964",
        "To": "1966",
        "Pos": "G",
        "Ht": "6-2",
        "Wt": "175",
        "Birth Date": "December 19 1938",
        "College": "University of Texas at Austin"
    },
    {
        "Player": "Bob Arnzen",
        "From": "1970",
        "To": "1974",
        "Pos": "F",
        "Ht": "6-5",
        "Wt": "205",
        "Birth Date": "November 3 1947",
        "College": "University of Notre Dame"
    },
    {
        "Player": "Carlos Arroyo",
        "From": "2002",
        "To": "2011",
        "Pos": "G",
        "Ht": "6-2",
        "Wt": "202",
        "Birth Date": "July 30 1979",
        "College": "Florida International University"
    },
    {
        "Player": "Darrell Arthur",
        "From": "2009",
        "To": "2015",
        "Pos": "F",
        "Ht": "6-9",
        "Wt": "225",
        "Birth Date": "March 25 1988",
        "College": "University of Kansas"
    },
    {
        "Player": "John Arthurs",
        "From": "1970",
        "To": "1970",
        "Pos": "G",
        "Ht": "6-4",
        "Wt": "185",
        "Birth Date": "August 15 1947",
        "College": "Tulane University"
    },
    {
        "Player": "Omer Asik",
        "From": "2011",
        "To": "2015",
        "Pos": "C",
        "Ht": "7-0",
        "Wt": "255",
        "Birth Date": "July 4 1986",
        "College": ""
    },
    {
        "Player": "Vincent Askew",
        "From": "1988",
        "To": "1998",
        "Pos": "G-F",
        "Ht": "6-6",
        "Wt": "210",
        "Birth Date": "February 28 1966",
        "College": "University of Memphis"
    },
    {
        "Player": "Keith Askins",
        "From": "1991",
        "To": "1999",
        "Pos": "G-F",
        "Ht": "6-7",
        "Wt": "197",
        "Birth Date": "December 15 1967",
        "College": "University of Alabama"
    },
    {
        "Player": "Don Asmonga",
        "From": "1954",
        "To": "1954",
        "Pos": "G",
        "Ht": "6-2",
        "Wt": "185",
        "Birth Date": "February 15 1928",
        "College": "Alliance College"
    },
    {
        "Player": "Dick Atha",
        "From": "1956",
        "To": "1958",
        "Pos": "G",
        "Ht": "6-2",
        "Wt": "190",
        "Birth Date": "September 21 1931",
        "College": "Indiana State University"
    },
    {
        "Player": "Chucky Atkins",
        "From": "2000",
        "To": "2010",
        "Pos": "G",
        "Ht": "5-11",
        "Wt": "160",
        "Birth Date": "August 14 1974",
        "College": "University of South Florida"
    },
    {
        "Player": "Al Attles",
        "From": "1961",
        "To": "1971",
        "Pos": "G",
        "Ht": "6-0",
        "Wt": "175",
        "Birth Date": "November 7 1936",
        "College": "North Carolina Agricultural and Technical State University"
    },
    {
        "Player": "Chet Aubuchon",
        "From": "1947",
        "To": "1947",
        "Pos": "G",
        "Ht": "5-10",
        "Wt": "137",
        "Birth Date": "May 18 1916",
        "College": "Michigan State University"
    },
    {
        "Player": "Stacey Augmon",
        "From": "1992",
        "To": "2006",
        "Pos": "F-G",
        "Ht": "6-6",
        "Wt": "205",
        "Birth Date": "August 1 1968",
        "College": "University of Nevada Las Vegas"
    },
    {
        "Player": "D.J. Augustin",
        "From": "2009",
        "To": "2015",
        "Pos": "G",
        "Ht": "6-0",
        "Wt": "180",
        "Birth Date": "November 10 1987",
        "College": "University of Texas at Austin"
    },
    {
        "Player": "James Augustine",
        "From": "2007",
        "To": "2008",
        "Pos": "F",
        "Ht": "6-10",
        "Wt": "235",
        "Birth Date": "February 27 1984",
        "College": "University of Illinois at Urbana-Champaign"
    },
    {
        "Player": "Isaac Austin",
        "From": "1992",
        "To": "2002",
        "Pos": "C",
        "Ht": "6-10",
        "Wt": "255",
        "Birth Date": "August 18 1969",
        "College": "Arizona State University"
    },
    {
        "Player": "Johnny Austin",
        "From": "1967",
        "To": "1968",
        "Pos": "G",
        "Ht": "6-0",
        "Wt": "170",
        "Birth Date": "August 31 1944",
        "College": "Boston College"
    },
    {
        "Player": "Ken Austin",
        "From": "1984",
        "To": "1984",
        "Pos": "F",
        "Ht": "6-9",
        "Wt": "205",
        "Birth Date": "July 15 1961",
        "College": "Rice University"
    },
    {
        "Player": "Anthony Avent",
        "From": "1993",
        "To": "2000",
        "Pos": "F",
        "Ht": "6-9",
        "Wt": "235",
        "Birth Date": "October 18 1969",
        "College": "Seton Hall University"
    },
    {
        "Player": "Bird Averitt",
        "From": "1974",
        "To": "1978",
        "Pos": "G",
        "Ht": "6-1",
        "Wt": "170",
        "Birth Date": "July 22 1952",
        "College": "Pepperdine University"
    },
    {
        "Player": "William Avery",
        "From": "2000",
        "To": "2002",
        "Pos": "G",
        "Ht": "6-2",
        "Wt": "197",
        "Birth Date": "August 8 1979",
        "College": "Duke University"
    },
    {
        "Player": "Dennis Awtrey",
        "From": "1971",
        "To": "1982",
        "Pos": "C",
        "Ht": "6-10",
        "Wt": "235",
        "Birth Date": "February 22 1948",
        "College": "Santa Clara University"
    },
    {
        "Player": "Gustavo Ayon",
        "From": "2012",
        "To": "2014",
        "Pos": "C",
        "Ht": "6-10",
        "Wt": "250",
        "Birth Date": "April 1 1985",
        "College": ""
    },
    {
        "Player": "Jeff Ayres",
        "From": "2010",
        "To": "2015",
        "Pos": "F",
        "Ht": "6-9",
        "Wt": "240",
        "Birth Date": "April 29 1987",
        "College": "Arizona State University"
    },
    {
        "Player": "Kelenna Azubuike",
        "From": "2007",
        "To": "2012",
        "Pos": "G",
        "Ht": "6-5",
        "Wt": "220",
        "Birth Date": "December 16 1983",
        "College": "University of Kentucky"
    }
]