[
    {
        "Player": "Bob Quick",
        "From": "1969",
        "To": "1972",
        "Pos": "F-G",
        "Ht": "6-5",
        "Wt": "215",
        "Birth Date": "March 5 1946",
        "College": "Xavier University"
    },
    {
        "Player": "Chris Quinn",
        "From": "2007",
        "To": "2013",
        "Pos": "G",
        "Ht": "6-2",
        "Wt": "185",
        "Birth Date": "September 27 1983",
        "College": "University of Notre Dame"
    },
    {
        "Player": "Brian Quinnett",
        "From": "1990",
        "To": "1992",
        "Pos": "F",
        "Ht": "6-8",
        "Wt": "235",
        "Birth Date": "May 30 1966",
        "College": "Washington State University"
    }
]