[
    {
        "Player": "Edwin Ubiles",
        "From": "2012",
        "To": "2012",
        "Pos": "G",
        "Ht": "6-6",
        "Wt": "204",
        "Birth Date": "November 26 1986",
        "College": "Siena College"
    },
    {
        "Player": "Ekpe Udoh",
        "From": "2011",
        "To": "2015",
        "Pos": "F",
        "Ht": "6-10",
        "Wt": "240",
        "Birth Date": "May 20 1987",
        "College": "Baylor University"
    },
    {
        "Player": "Ime Udoka",
        "From": "2004",
        "To": "2011",
        "Pos": "F",
        "Ht": "6-6",
        "Wt": "215",
        "Birth Date": "August 9 1977",
        "College": "Portland State University"
    },
    {
        "Player": "Beno Udrih",
        "From": "2005",
        "To": "2015",
        "Pos": "G",
        "Ht": "6-3",
        "Wt": "205",
        "Birth Date": "July 5 1982",
        "College": ""
    },
    {
        "Player": "Roko Ukic",
        "From": "2009",
        "To": "2010",
        "Pos": "G",
        "Ht": "6-5",
        "Wt": "183",
        "Birth Date": "May 12 1984",
        "College": ""
    },
    {
        "Player": "Wes Unseld*",
        "From": "1969",
        "To": "1981",
        "Pos": "C-F",
        "Ht": "6-7",
        "Wt": "245",
        "Birth Date": "March 14 1946",
        "College": "University of Louisville"
    },
    {
        "Player": "Hal Uplinger",
        "From": "1954",
        "To": "1954",
        "Pos": "G",
        "Ht": "6-4",
        "Wt": "185",
        "Birth Date": "September 30 1929",
        "College": "Long Island University"
    },
    {
        "Player": "Kelvin Upshaw",
        "From": "1989",
        "To": "1991",
        "Pos": "G",
        "Ht": "6-2",
        "Wt": "180",
        "Birth Date": "January 24 1963",
        "College": "University of Utah"
    },
    {
        "Player": "Ben Uzoh",
        "From": "2011",
        "To": "2012",
        "Pos": "G",
        "Ht": "6-3",
        "Wt": "205",
        "Birth Date": "March 19 1988",
        "College": "University of Tulsa"
    }
]